package net.minecraft.server.commands;

import com.mojang.brigadier.exceptions.CommandSyntaxException;
import net.minecraft.world.entity.Entity;
import net.minecraft.Util;
import net.minecraft.network.chat.Component;
import net.minecraft.network.chat.ChatType;
import net.minecraft.network.chat.TranslatableComponent;
import com.mojang.brigadier.arguments.StringArgumentType;
import com.mojang.brigadier.context.CommandContext;
import net.minecraft.commands.CommandSourceStack;
import com.mojang.brigadier.CommandDispatcher;

public class EmoteCommands {
    public static void register(final CommandDispatcher<CommandSourceStack> commandDispatcher) {
        // 
        // This method could not be decompiled.
        // 
        // Original Bytecode:
        // 
        //     1: ldc             "me"
        //     3: invokestatic    net/minecraft/commands/Commands.literal:(Ljava/lang/String;)Lcom/mojang/brigadier/builder/LiteralArgumentBuilder;
        //     6: ldc             "action"
        //     8: invokestatic    com/mojang/brigadier/arguments/StringArgumentType.greedyString:()Lcom/mojang/brigadier/arguments/StringArgumentType;
        //    11: invokestatic    net/minecraft/commands/Commands.argument:(Ljava/lang/String;Lcom/mojang/brigadier/arguments/ArgumentType;)Lcom/mojang/brigadier/builder/RequiredArgumentBuilder;
        //    14: invokedynamic   BootstrapMethod #0, run:()Lcom/mojang/brigadier/Command;
        //    19: invokevirtual   com/mojang/brigadier/builder/RequiredArgumentBuilder.executes:(Lcom/mojang/brigadier/Command;)Lcom/mojang/brigadier/builder/ArgumentBuilder;
        //    22: invokevirtual   com/mojang/brigadier/builder/LiteralArgumentBuilder.then:(Lcom/mojang/brigadier/builder/ArgumentBuilder;)Lcom/mojang/brigadier/builder/ArgumentBuilder;
        //    25: checkcast       Lcom/mojang/brigadier/builder/LiteralArgumentBuilder;
        //    28: invokevirtual   com/mojang/brigadier/CommandDispatcher.register:(Lcom/mojang/brigadier/builder/LiteralArgumentBuilder;)Lcom/mojang/brigadier/tree/LiteralCommandNode;
        //    31: pop            
        //    32: return         
        //    Signature:
        //  (Lcom/mojang/brigadier/CommandDispatcher<Lnet/minecraft/commands/CommandSourceStack;>;)V
        //    MethodParameters:
        //  Name               Flags  
        //  -----------------  -----
        //  commandDispatcher  
        // 
        // The error that occurred was:
        // 
        // java.lang.IllegalStateException: Could not infer any expression.
        //     at com.strobel.decompiler.ast.TypeAnalysis.runInference(TypeAnalysis.java:374)
        //     at com.strobel.decompiler.ast.TypeAnalysis.run(TypeAnalysis.java:96)
        //     at com.strobel.decompiler.ast.AstOptimizer.optimize(AstOptimizer.java:344)
        //     at com.strobel.decompiler.ast.AstOptimizer.optimize(AstOptimizer.java:42)
        //     at com.strobel.decompiler.languages.java.ast.AstMethodBodyBuilder.createMethodBody(AstMethodBodyBuilder.java:214)
        //     at com.strobel.decompiler.languages.java.ast.AstMethodBodyBuilder.createMethodBody(AstMethodBodyBuilder.java:99)
        //     at com.strobel.decompiler.languages.java.ast.AstBuilder.createMethodBody(AstBuilder.java:782)
        //     at com.strobel.decompiler.languages.java.ast.AstBuilder.createMethod(AstBuilder.java:675)
        //     at com.strobel.decompiler.languages.java.ast.AstBuilder.addTypeMembers(AstBuilder.java:552)
        //     at com.strobel.decompiler.languages.java.ast.AstBuilder.createTypeCore(AstBuilder.java:519)
        //     at com.strobel.decompiler.languages.java.ast.AstBuilder.createTypeNoCache(AstBuilder.java:161)
        //     at com.strobel.decompiler.languages.java.ast.AstBuilder.createType(AstBuilder.java:150)
        //     at com.strobel.decompiler.languages.java.ast.AstBuilder.addType(AstBuilder.java:125)
        //     at cuchaz.enigma.source.procyon.ProcyonDecompiler.getSource(ProcyonDecompiler.java:75)
        //     at cuchaz.enigma.EnigmaProject$JarExport.decompileClass(EnigmaProject.java:270)
        //     at cuchaz.enigma.EnigmaProject$JarExport.lambda$decompileStream$1(EnigmaProject.java:246)
        //     at java.base/java.util.stream.ReferencePipeline$3$1.accept(ReferencePipeline.java:195)
        //     at java.base/java.util.ArrayList$ArrayListSpliterator.forEachRemaining(ArrayList.java:1624)
        //     at java.base/java.util.stream.AbstractPipeline.copyInto(AbstractPipeline.java:484)
        //     at java.base/java.util.stream.ForEachOps$ForEachTask.compute(ForEachOps.java:290)
        //     at java.base/java.util.concurrent.CountedCompleter.exec(CountedCompleter.java:746)
        //     at java.base/java.util.concurrent.ForkJoinTask.doExec(ForkJoinTask.java:290)
        //     at java.base/java.util.concurrent.ForkJoinPool$WorkQueue.topLevelExec(ForkJoinPool.java:1016)
        //     at java.base/java.util.concurrent.ForkJoinPool.scan(ForkJoinPool.java:1665)
        //     at java.base/java.util.concurrent.ForkJoinPool.runWorker(ForkJoinPool.java:1598)
        //     at java.base/java.util.concurrent.ForkJoinWorkerThread.run(ForkJoinWorkerThread.java:177)
        // 
        throw new IllegalStateException("An error occurred while decompiling this method.");
    }
}
