package net.minecraft.util.datafix.fixes;

import java.util.function.Function;
import com.mojang.datafixers.schemas.Schema;
import java.util.Map;

public class AdvancementsFix extends AdvancementsRenameFix {
    private static final Map<String, String> RENAMES;
    
    public AdvancementsFix(final Schema schema, final boolean boolean2) {
        super(schema, boolean2, "AdvancementsFix", (Function<String, String>)(string -> (String)AdvancementsFix.RENAMES.getOrDefault(string, string)));
    }
    
    static {
        // 
        // This method could not be decompiled.
        // 
        // Original Bytecode:
        // 
        //     3: ldc             "minecraft:recipes/brewing/speckled_melon"
        //     5: ldc             "minecraft:recipes/brewing/glistering_melon_slice"
        //     7: invokevirtual   com/google/common/collect/ImmutableMap$Builder.put:(Ljava/lang/Object;Ljava/lang/Object;)Lcom/google/common/collect/ImmutableMap$Builder;
        //    10: ldc             "minecraft:recipes/building_blocks/black_stained_hardened_clay"
        //    12: ldc             "minecraft:recipes/building_blocks/black_terracotta"
        //    14: invokevirtual   com/google/common/collect/ImmutableMap$Builder.put:(Ljava/lang/Object;Ljava/lang/Object;)Lcom/google/common/collect/ImmutableMap$Builder;
        //    17: ldc             "minecraft:recipes/building_blocks/blue_stained_hardened_clay"
        //    19: ldc             "minecraft:recipes/building_blocks/blue_terracotta"
        //    21: invokevirtual   com/google/common/collect/ImmutableMap$Builder.put:(Ljava/lang/Object;Ljava/lang/Object;)Lcom/google/common/collect/ImmutableMap$Builder;
        //    24: ldc             "minecraft:recipes/building_blocks/brown_stained_hardened_clay"
        //    26: ldc             "minecraft:recipes/building_blocks/brown_terracotta"
        //    28: invokevirtual   com/google/common/collect/ImmutableMap$Builder.put:(Ljava/lang/Object;Ljava/lang/Object;)Lcom/google/common/collect/ImmutableMap$Builder;
        //    31: ldc             "minecraft:recipes/building_blocks/cyan_stained_hardened_clay"
        //    33: ldc             "minecraft:recipes/building_blocks/cyan_terracotta"
        //    35: invokevirtual   com/google/common/collect/ImmutableMap$Builder.put:(Ljava/lang/Object;Ljava/lang/Object;)Lcom/google/common/collect/ImmutableMap$Builder;
        //    38: ldc             "minecraft:recipes/building_blocks/gray_stained_hardened_clay"
        //    40: ldc             "minecraft:recipes/building_blocks/gray_terracotta"
        //    42: invokevirtual   com/google/common/collect/ImmutableMap$Builder.put:(Ljava/lang/Object;Ljava/lang/Object;)Lcom/google/common/collect/ImmutableMap$Builder;
        //    45: ldc             "minecraft:recipes/building_blocks/green_stained_hardened_clay"
        //    47: ldc             "minecraft:recipes/building_blocks/green_terracotta"
        //    49: invokevirtual   com/google/common/collect/ImmutableMap$Builder.put:(Ljava/lang/Object;Ljava/lang/Object;)Lcom/google/common/collect/ImmutableMap$Builder;
        //    52: ldc             "minecraft:recipes/building_blocks/light_blue_stained_hardened_clay"
        //    54: ldc             "minecraft:recipes/building_blocks/light_blue_terracotta"
        //    56: invokevirtual   com/google/common/collect/ImmutableMap$Builder.put:(Ljava/lang/Object;Ljava/lang/Object;)Lcom/google/common/collect/ImmutableMap$Builder;
        //    59: ldc             "minecraft:recipes/building_blocks/light_gray_stained_hardened_clay"
        //    61: ldc             "minecraft:recipes/building_blocks/light_gray_terracotta"
        //    63: invokevirtual   com/google/common/collect/ImmutableMap$Builder.put:(Ljava/lang/Object;Ljava/lang/Object;)Lcom/google/common/collect/ImmutableMap$Builder;
        //    66: ldc             "minecraft:recipes/building_blocks/lime_stained_hardened_clay"
        //    68: ldc             "minecraft:recipes/building_blocks/lime_terracotta"
        //    70: invokevirtual   com/google/common/collect/ImmutableMap$Builder.put:(Ljava/lang/Object;Ljava/lang/Object;)Lcom/google/common/collect/ImmutableMap$Builder;
        //    73: ldc             "minecraft:recipes/building_blocks/magenta_stained_hardened_clay"
        //    75: ldc             "minecraft:recipes/building_blocks/magenta_terracotta"
        //    77: invokevirtual   com/google/common/collect/ImmutableMap$Builder.put:(Ljava/lang/Object;Ljava/lang/Object;)Lcom/google/common/collect/ImmutableMap$Builder;
        //    80: ldc             "minecraft:recipes/building_blocks/orange_stained_hardened_clay"
        //    82: ldc             "minecraft:recipes/building_blocks/orange_terracotta"
        //    84: invokevirtual   com/google/common/collect/ImmutableMap$Builder.put:(Ljava/lang/Object;Ljava/lang/Object;)Lcom/google/common/collect/ImmutableMap$Builder;
        //    87: ldc             "minecraft:recipes/building_blocks/pink_stained_hardened_clay"
        //    89: ldc             "minecraft:recipes/building_blocks/pink_terracotta"
        //    91: invokevirtual   com/google/common/collect/ImmutableMap$Builder.put:(Ljava/lang/Object;Ljava/lang/Object;)Lcom/google/common/collect/ImmutableMap$Builder;
        //    94: ldc             "minecraft:recipes/building_blocks/purple_stained_hardened_clay"
        //    96: ldc             "minecraft:recipes/building_blocks/purple_terracotta"
        //    98: invokevirtual   com/google/common/collect/ImmutableMap$Builder.put:(Ljava/lang/Object;Ljava/lang/Object;)Lcom/google/common/collect/ImmutableMap$Builder;
        //   101: ldc             "minecraft:recipes/building_blocks/red_stained_hardened_clay"
        //   103: ldc             "minecraft:recipes/building_blocks/red_terracotta"
        //   105: invokevirtual   com/google/common/collect/ImmutableMap$Builder.put:(Ljava/lang/Object;Ljava/lang/Object;)Lcom/google/common/collect/ImmutableMap$Builder;
        //   108: ldc             "minecraft:recipes/building_blocks/white_stained_hardened_clay"
        //   110: ldc             "minecraft:recipes/building_blocks/white_terracotta"
        //   112: invokevirtual   com/google/common/collect/ImmutableMap$Builder.put:(Ljava/lang/Object;Ljava/lang/Object;)Lcom/google/common/collect/ImmutableMap$Builder;
        //   115: ldc             "minecraft:recipes/building_blocks/yellow_stained_hardened_clay"
        //   117: ldc             "minecraft:recipes/building_blocks/yellow_terracotta"
        //   119: invokevirtual   com/google/common/collect/ImmutableMap$Builder.put:(Ljava/lang/Object;Ljava/lang/Object;)Lcom/google/common/collect/ImmutableMap$Builder;
        //   122: ldc             "minecraft:recipes/building_blocks/acacia_wooden_slab"
        //   124: ldc             "minecraft:recipes/building_blocks/acacia_slab"
        //   126: invokevirtual   com/google/common/collect/ImmutableMap$Builder.put:(Ljava/lang/Object;Ljava/lang/Object;)Lcom/google/common/collect/ImmutableMap$Builder;
        //   129: ldc             "minecraft:recipes/building_blocks/birch_wooden_slab"
        //   131: ldc             "minecraft:recipes/building_blocks/birch_slab"
        //   133: invokevirtual   com/google/common/collect/ImmutableMap$Builder.put:(Ljava/lang/Object;Ljava/lang/Object;)Lcom/google/common/collect/ImmutableMap$Builder;
        //   136: ldc             "minecraft:recipes/building_blocks/dark_oak_wooden_slab"
        //   138: ldc             "minecraft:recipes/building_blocks/dark_oak_slab"
        //   140: invokevirtual   com/google/common/collect/ImmutableMap$Builder.put:(Ljava/lang/Object;Ljava/lang/Object;)Lcom/google/common/collect/ImmutableMap$Builder;
        //   143: ldc             "minecraft:recipes/building_blocks/jungle_wooden_slab"
        //   145: ldc             "minecraft:recipes/building_blocks/jungle_slab"
        //   147: invokevirtual   com/google/common/collect/ImmutableMap$Builder.put:(Ljava/lang/Object;Ljava/lang/Object;)Lcom/google/common/collect/ImmutableMap$Builder;
        //   150: ldc             "minecraft:recipes/building_blocks/oak_wooden_slab"
        //   152: ldc             "minecraft:recipes/building_blocks/oak_slab"
        //   154: invokevirtual   com/google/common/collect/ImmutableMap$Builder.put:(Ljava/lang/Object;Ljava/lang/Object;)Lcom/google/common/collect/ImmutableMap$Builder;
        //   157: ldc             "minecraft:recipes/building_blocks/spruce_wooden_slab"
        //   159: ldc             "minecraft:recipes/building_blocks/spruce_slab"
        //   161: invokevirtual   com/google/common/collect/ImmutableMap$Builder.put:(Ljava/lang/Object;Ljava/lang/Object;)Lcom/google/common/collect/ImmutableMap$Builder;
        //   164: ldc             "minecraft:recipes/building_blocks/brick_block"
        //   166: ldc             "minecraft:recipes/building_blocks/bricks"
        //   168: invokevirtual   com/google/common/collect/ImmutableMap$Builder.put:(Ljava/lang/Object;Ljava/lang/Object;)Lcom/google/common/collect/ImmutableMap$Builder;
        //   171: ldc             "minecraft:recipes/building_blocks/chiseled_stonebrick"
        //   173: ldc             "minecraft:recipes/building_blocks/chiseled_stone_bricks"
        //   175: invokevirtual   com/google/common/collect/ImmutableMap$Builder.put:(Ljava/lang/Object;Ljava/lang/Object;)Lcom/google/common/collect/ImmutableMap$Builder;
        //   178: ldc             "minecraft:recipes/building_blocks/end_bricks"
        //   180: ldc             "minecraft:recipes/building_blocks/end_stone_bricks"
        //   182: invokevirtual   com/google/common/collect/ImmutableMap$Builder.put:(Ljava/lang/Object;Ljava/lang/Object;)Lcom/google/common/collect/ImmutableMap$Builder;
        //   185: ldc             "minecraft:recipes/building_blocks/lit_pumpkin"
        //   187: ldc             "minecraft:recipes/building_blocks/jack_o_lantern"
        //   189: invokevirtual   com/google/common/collect/ImmutableMap$Builder.put:(Ljava/lang/Object;Ljava/lang/Object;)Lcom/google/common/collect/ImmutableMap$Builder;
        //   192: ldc             "minecraft:recipes/building_blocks/magma"
        //   194: ldc             "minecraft:recipes/building_blocks/magma_block"
        //   196: invokevirtual   com/google/common/collect/ImmutableMap$Builder.put:(Ljava/lang/Object;Ljava/lang/Object;)Lcom/google/common/collect/ImmutableMap$Builder;
        //   199: ldc             "minecraft:recipes/building_blocks/melon_block"
        //   201: ldc             "minecraft:recipes/building_blocks/melon"
        //   203: invokevirtual   com/google/common/collect/ImmutableMap$Builder.put:(Ljava/lang/Object;Ljava/lang/Object;)Lcom/google/common/collect/ImmutableMap$Builder;
        //   206: ldc             "minecraft:recipes/building_blocks/mossy_stonebrick"
        //   208: ldc             "minecraft:recipes/building_blocks/mossy_stone_bricks"
        //   210: invokevirtual   com/google/common/collect/ImmutableMap$Builder.put:(Ljava/lang/Object;Ljava/lang/Object;)Lcom/google/common/collect/ImmutableMap$Builder;
        //   213: ldc             "minecraft:recipes/building_blocks/nether_brick"
        //   215: ldc             "minecraft:recipes/building_blocks/nether_bricks"
        //   217: invokevirtual   com/google/common/collect/ImmutableMap$Builder.put:(Ljava/lang/Object;Ljava/lang/Object;)Lcom/google/common/collect/ImmutableMap$Builder;
        //   220: ldc             "minecraft:recipes/building_blocks/pillar_quartz_block"
        //   222: ldc             "minecraft:recipes/building_blocks/quartz_pillar"
        //   224: invokevirtual   com/google/common/collect/ImmutableMap$Builder.put:(Ljava/lang/Object;Ljava/lang/Object;)Lcom/google/common/collect/ImmutableMap$Builder;
        //   227: ldc             "minecraft:recipes/building_blocks/red_nether_brick"
        //   229: ldc             "minecraft:recipes/building_blocks/red_nether_bricks"
        //   231: invokevirtual   com/google/common/collect/ImmutableMap$Builder.put:(Ljava/lang/Object;Ljava/lang/Object;)Lcom/google/common/collect/ImmutableMap$Builder;
        //   234: ldc             "minecraft:recipes/building_blocks/snow"
        //   236: ldc             "minecraft:recipes/building_blocks/snow_block"
        //   238: invokevirtual   com/google/common/collect/ImmutableMap$Builder.put:(Ljava/lang/Object;Ljava/lang/Object;)Lcom/google/common/collect/ImmutableMap$Builder;
        //   241: ldc             "minecraft:recipes/building_blocks/smooth_red_sandstone"
        //   243: ldc             "minecraft:recipes/building_blocks/cut_red_sandstone"
        //   245: invokevirtual   com/google/common/collect/ImmutableMap$Builder.put:(Ljava/lang/Object;Ljava/lang/Object;)Lcom/google/common/collect/ImmutableMap$Builder;
        //   248: ldc             "minecraft:recipes/building_blocks/smooth_sandstone"
        //   250: ldc             "minecraft:recipes/building_blocks/cut_sandstone"
        //   252: invokevirtual   com/google/common/collect/ImmutableMap$Builder.put:(Ljava/lang/Object;Ljava/lang/Object;)Lcom/google/common/collect/ImmutableMap$Builder;
        //   255: ldc             "minecraft:recipes/building_blocks/stonebrick"
        //   257: ldc             "minecraft:recipes/building_blocks/stone_bricks"
        //   259: invokevirtual   com/google/common/collect/ImmutableMap$Builder.put:(Ljava/lang/Object;Ljava/lang/Object;)Lcom/google/common/collect/ImmutableMap$Builder;
        //   262: ldc             "minecraft:recipes/building_blocks/stone_stairs"
        //   264: ldc             "minecraft:recipes/building_blocks/cobblestone_stairs"
        //   266: invokevirtual   com/google/common/collect/ImmutableMap$Builder.put:(Ljava/lang/Object;Ljava/lang/Object;)Lcom/google/common/collect/ImmutableMap$Builder;
        //   269: ldc             "minecraft:recipes/building_blocks/string_to_wool"
        //   271: ldc             "minecraft:recipes/building_blocks/white_wool_from_string"
        //   273: invokevirtual   com/google/common/collect/ImmutableMap$Builder.put:(Ljava/lang/Object;Ljava/lang/Object;)Lcom/google/common/collect/ImmutableMap$Builder;
        //   276: ldc             "minecraft:recipes/decorations/fence"
        //   278: ldc             "minecraft:recipes/decorations/oak_fence"
        //   280: invokevirtual   com/google/common/collect/ImmutableMap$Builder.put:(Ljava/lang/Object;Ljava/lang/Object;)Lcom/google/common/collect/ImmutableMap$Builder;
        //   283: ldc             "minecraft:recipes/decorations/purple_shulker_box"
        //   285: ldc             "minecraft:recipes/decorations/shulker_box"
        //   287: invokevirtual   com/google/common/collect/ImmutableMap$Builder.put:(Ljava/lang/Object;Ljava/lang/Object;)Lcom/google/common/collect/ImmutableMap$Builder;
        //   290: ldc             "minecraft:recipes/decorations/slime"
        //   292: ldc             "minecraft:recipes/decorations/slime_block"
        //   294: invokevirtual   com/google/common/collect/ImmutableMap$Builder.put:(Ljava/lang/Object;Ljava/lang/Object;)Lcom/google/common/collect/ImmutableMap$Builder;
        //   297: ldc             "minecraft:recipes/decorations/snow_layer"
        //   299: ldc             "minecraft:recipes/decorations/snow"
        //   301: invokevirtual   com/google/common/collect/ImmutableMap$Builder.put:(Ljava/lang/Object;Ljava/lang/Object;)Lcom/google/common/collect/ImmutableMap$Builder;
        //   304: ldc             "minecraft:recipes/misc/bone_meal_from_block"
        //   306: ldc             "minecraft:recipes/misc/bone_meal_from_bone_block"
        //   308: invokevirtual   com/google/common/collect/ImmutableMap$Builder.put:(Ljava/lang/Object;Ljava/lang/Object;)Lcom/google/common/collect/ImmutableMap$Builder;
        //   311: ldc             "minecraft:recipes/misc/bone_meal_from_bone"
        //   313: ldc             "minecraft:recipes/misc/bone_meal"
        //   315: invokevirtual   com/google/common/collect/ImmutableMap$Builder.put:(Ljava/lang/Object;Ljava/lang/Object;)Lcom/google/common/collect/ImmutableMap$Builder;
        //   318: ldc             "minecraft:recipes/misc/gold_ingot_from_block"
        //   320: ldc_w           "minecraft:recipes/misc/gold_ingot_from_gold_block"
        //   323: invokevirtual   com/google/common/collect/ImmutableMap$Builder.put:(Ljava/lang/Object;Ljava/lang/Object;)Lcom/google/common/collect/ImmutableMap$Builder;
        //   326: ldc_w           "minecraft:recipes/misc/iron_ingot_from_block"
        //   329: ldc_w           "minecraft:recipes/misc/iron_ingot_from_iron_block"
        //   332: invokevirtual   com/google/common/collect/ImmutableMap$Builder.put:(Ljava/lang/Object;Ljava/lang/Object;)Lcom/google/common/collect/ImmutableMap$Builder;
        //   335: ldc_w           "minecraft:recipes/redstone/fence_gate"
        //   338: ldc_w           "minecraft:recipes/redstone/oak_fence_gate"
        //   341: invokevirtual   com/google/common/collect/ImmutableMap$Builder.put:(Ljava/lang/Object;Ljava/lang/Object;)Lcom/google/common/collect/ImmutableMap$Builder;
        //   344: ldc_w           "minecraft:recipes/redstone/noteblock"
        //   347: ldc_w           "minecraft:recipes/redstone/note_block"
        //   350: invokevirtual   com/google/common/collect/ImmutableMap$Builder.put:(Ljava/lang/Object;Ljava/lang/Object;)Lcom/google/common/collect/ImmutableMap$Builder;
        //   353: ldc_w           "minecraft:recipes/redstone/trapdoor"
        //   356: ldc_w           "minecraft:recipes/redstone/oak_trapdoor"
        //   359: invokevirtual   com/google/common/collect/ImmutableMap$Builder.put:(Ljava/lang/Object;Ljava/lang/Object;)Lcom/google/common/collect/ImmutableMap$Builder;
        //   362: ldc_w           "minecraft:recipes/redstone/wooden_button"
        //   365: ldc_w           "minecraft:recipes/redstone/oak_button"
        //   368: invokevirtual   com/google/common/collect/ImmutableMap$Builder.put:(Ljava/lang/Object;Ljava/lang/Object;)Lcom/google/common/collect/ImmutableMap$Builder;
        //   371: ldc_w           "minecraft:recipes/redstone/wooden_door"
        //   374: ldc_w           "minecraft:recipes/redstone/oak_door"
        //   377: invokevirtual   com/google/common/collect/ImmutableMap$Builder.put:(Ljava/lang/Object;Ljava/lang/Object;)Lcom/google/common/collect/ImmutableMap$Builder;
        //   380: ldc_w           "minecraft:recipes/redstone/wooden_pressure_plate"
        //   383: ldc_w           "minecraft:recipes/redstone/oak_pressure_plate"
        //   386: invokevirtual   com/google/common/collect/ImmutableMap$Builder.put:(Ljava/lang/Object;Ljava/lang/Object;)Lcom/google/common/collect/ImmutableMap$Builder;
        //   389: ldc_w           "minecraft:recipes/transportation/boat"
        //   392: ldc_w           "minecraft:recipes/transportation/oak_boat"
        //   395: invokevirtual   com/google/common/collect/ImmutableMap$Builder.put:(Ljava/lang/Object;Ljava/lang/Object;)Lcom/google/common/collect/ImmutableMap$Builder;
        //   398: ldc_w           "minecraft:recipes/transportation/golden_rail"
        //   401: ldc_w           "minecraft:recipes/transportation/powered_rail"
        //   404: invokevirtual   com/google/common/collect/ImmutableMap$Builder.put:(Ljava/lang/Object;Ljava/lang/Object;)Lcom/google/common/collect/ImmutableMap$Builder;
        //   407: invokevirtual   com/google/common/collect/ImmutableMap$Builder.build:()Lcom/google/common/collect/ImmutableMap;
        //   410: putstatic       net/minecraft/util/datafix/fixes/AdvancementsFix.RENAMES:Ljava/util/Map;
        //   413: return         
        // 
        // The error that occurred was:
        // 
        // java.lang.ArrayIndexOutOfBoundsException: Array index out of range: 2
        //     at java.base/java.util.Vector.get(Vector.java:749)
        //     at com.strobel.assembler.metadata.MetadataResolver.resolve(MetadataResolver.java:82)
        //     at com.strobel.assembler.metadata.CoreMetadataFactory$UnresolvedType.resolve(CoreMetadataFactory.java:616)
        //     at com.strobel.assembler.metadata.MetadataResolver.resolve(MetadataResolver.java:91)
        //     at com.strobel.assembler.metadata.CoreMetadataFactory$UnresolvedType.resolve(CoreMetadataFactory.java:616)
        //     at com.strobel.assembler.metadata.ParameterizedType.resolve(ParameterizedType.java:108)
        //     at com.strobel.assembler.metadata.MetadataHelper.getGenericSubTypeMappings(MetadataHelper.java:761)
        //     at com.strobel.decompiler.ast.TypeAnalysis.inferCall(TypeAnalysis.java:2503)
        //     at com.strobel.decompiler.ast.TypeAnalysis.doInferTypeForExpression(TypeAnalysis.java:1029)
        //     at com.strobel.decompiler.ast.TypeAnalysis.inferTypeForExpression(TypeAnalysis.java:803)
        //     at com.strobel.decompiler.ast.TypeAnalysis.inferTypeForExpression(TypeAnalysis.java:778)
        //     at com.strobel.decompiler.ast.TypeAnalysis.inferCall(TypeAnalysis.java:2669)
        //     at com.strobel.decompiler.ast.TypeAnalysis.doInferTypeForExpression(TypeAnalysis.java:1029)
        //     at com.strobel.decompiler.ast.TypeAnalysis.inferTypeForExpression(TypeAnalysis.java:803)
        //     at com.strobel.decompiler.ast.TypeAnalysis.inferTypeForExpression(TypeAnalysis.java:778)
        //     at com.strobel.decompiler.ast.TypeAnalysis.inferCall(TypeAnalysis.java:2669)
        //     at com.strobel.decompiler.ast.TypeAnalysis.doInferTypeForExpression(TypeAnalysis.java:1029)
        //     at com.strobel.decompiler.ast.TypeAnalysis.inferTypeForExpression(TypeAnalysis.java:803)
        //     at com.strobel.decompiler.ast.TypeAnalysis.inferTypeForExpression(TypeAnalysis.java:778)
        //     at com.strobel.decompiler.ast.TypeAnalysis.inferCall(TypeAnalysis.java:2669)
        //     at com.strobel.decompiler.ast.TypeAnalysis.doInferTypeForExpression(TypeAnalysis.java:1029)
        //     at com.strobel.decompiler.ast.TypeAnalysis.inferTypeForExpression(TypeAnalysis.java:803)
        //     at com.strobel.decompiler.ast.TypeAnalysis.inferTypeForExpression(TypeAnalysis.java:778)
        //     at com.strobel.decompiler.ast.TypeAnalysis.inferCall(TypeAnalysis.java:2669)
        //     at com.strobel.decompiler.ast.TypeAnalysis.doInferTypeForExpression(TypeAnalysis.java:1029)
        //     at com.strobel.decompiler.ast.TypeAnalysis.inferTypeForExpression(TypeAnalysis.java:803)
        //     at com.strobel.decompiler.ast.TypeAnalysis.inferTypeForExpression(TypeAnalysis.java:778)
        //     at com.strobel.decompiler.ast.TypeAnalysis.inferCall(TypeAnalysis.java:2669)
        //     at com.strobel.decompiler.ast.TypeAnalysis.doInferTypeForExpression(TypeAnalysis.java:1029)
        //     at com.strobel.decompiler.ast.TypeAnalysis.inferTypeForExpression(TypeAnalysis.java:803)
        //     at com.strobel.decompiler.ast.TypeAnalysis.inferTypeForExpression(TypeAnalysis.java:778)
        //     at com.strobel.decompiler.ast.TypeAnalysis.inferCall(TypeAnalysis.java:2669)
        //     at com.strobel.decompiler.ast.TypeAnalysis.doInferTypeForExpression(TypeAnalysis.java:1029)
        //     at com.strobel.decompiler.ast.TypeAnalysis.inferTypeForExpression(TypeAnalysis.java:803)
        //     at com.strobel.decompiler.ast.TypeAnalysis.inferTypeForExpression(TypeAnalysis.java:778)
        //     at com.strobel.decompiler.ast.TypeAnalysis.inferCall(TypeAnalysis.java:2669)
        //     at com.strobel.decompiler.ast.TypeAnalysis.doInferTypeForExpression(TypeAnalysis.java:1029)
        //     at com.strobel.decompiler.ast.TypeAnalysis.inferTypeForExpression(TypeAnalysis.java:803)
        //     at com.strobel.decompiler.ast.TypeAnalysis.inferTypeForExpression(TypeAnalysis.java:778)
        //     at com.strobel.decompiler.ast.TypeAnalysis.inferCall(TypeAnalysis.java:2669)
        //     at com.strobel.decompiler.ast.TypeAnalysis.doInferTypeForExpression(TypeAnalysis.java:1029)
        //     at com.strobel.decompiler.ast.TypeAnalysis.inferTypeForExpression(TypeAnalysis.java:803)
        //     at com.strobel.decompiler.ast.TypeAnalysis.inferTypeForExpression(TypeAnalysis.java:778)
        //     at com.strobel.decompiler.ast.TypeAnalysis.inferCall(TypeAnalysis.java:2669)
        //     at com.strobel.decompiler.ast.TypeAnalysis.doInferTypeForExpression(TypeAnalysis.java:1029)
        //     at com.strobel.decompiler.ast.TypeAnalysis.inferTypeForExpression(TypeAnalysis.java:803)
        //     at com.strobel.decompiler.ast.TypeAnalysis.inferTypeForExpression(TypeAnalysis.java:778)
        //     at com.strobel.decompiler.ast.TypeAnalysis.inferCall(TypeAnalysis.java:2669)
        //     at com.strobel.decompiler.ast.TypeAnalysis.doInferTypeForExpression(TypeAnalysis.java:1029)
        //     at com.strobel.decompiler.ast.TypeAnalysis.inferTypeForExpression(TypeAnalysis.java:803)
        //     at com.strobel.decompiler.ast.TypeAnalysis.inferTypeForExpression(TypeAnalysis.java:778)
        //     at com.strobel.decompiler.ast.TypeAnalysis.inferCall(TypeAnalysis.java:2669)
        //     at com.strobel.decompiler.ast.TypeAnalysis.doInferTypeForExpression(TypeAnalysis.java:1029)
        //     at com.strobel.decompiler.ast.TypeAnalysis.inferTypeForExpression(TypeAnalysis.java:803)
        //     at com.strobel.decompiler.ast.TypeAnalysis.inferTypeForExpression(TypeAnalysis.java:778)
        //     at com.strobel.decompiler.ast.TypeAnalysis.inferCall(TypeAnalysis.java:2669)
        //     at com.strobel.decompiler.ast.TypeAnalysis.doInferTypeForExpression(TypeAnalysis.java:1029)
        //     at com.strobel.decompiler.ast.TypeAnalysis.inferTypeForExpression(TypeAnalysis.java:803)
        //     at com.strobel.decompiler.ast.TypeAnalysis.inferTypeForExpression(TypeAnalysis.java:778)
        //     at com.strobel.decompiler.ast.TypeAnalysis.inferCall(TypeAnalysis.java:2669)
        //     at com.strobel.decompiler.ast.TypeAnalysis.doInferTypeForExpression(TypeAnalysis.java:1029)
        //     at com.strobel.decompiler.ast.TypeAnalysis.inferTypeForExpression(TypeAnalysis.java:803)
        //     at com.strobel.decompiler.ast.TypeAnalysis.inferTypeForExpression(TypeAnalysis.java:778)
        //     at com.strobel.decompiler.ast.TypeAnalysis.inferCall(TypeAnalysis.java:2669)
        //     at com.strobel.decompiler.ast.TypeAnalysis.doInferTypeForExpression(TypeAnalysis.java:1029)
        //     at com.strobel.decompiler.ast.TypeAnalysis.inferTypeForExpression(TypeAnalysis.java:803)
        //     at com.strobel.decompiler.ast.TypeAnalysis.inferTypeForExpression(TypeAnalysis.java:778)
        //     at com.strobel.decompiler.ast.TypeAnalysis.inferCall(TypeAnalysis.java:2669)
        //     at com.strobel.decompiler.ast.TypeAnalysis.doInferTypeForExpression(TypeAnalysis.java:1029)
        //     at com.strobel.decompiler.ast.TypeAnalysis.inferTypeForExpression(TypeAnalysis.java:803)
        //     at com.strobel.decompiler.ast.TypeAnalysis.inferTypeForExpression(TypeAnalysis.java:778)
        //     at com.strobel.decompiler.ast.TypeAnalysis.inferCall(TypeAnalysis.java:2669)
        //     at com.strobel.decompiler.ast.TypeAnalysis.doInferTypeForExpression(TypeAnalysis.java:1029)
        //     at com.strobel.decompiler.ast.TypeAnalysis.inferTypeForExpression(TypeAnalysis.java:803)
        //     at com.strobel.decompiler.ast.TypeAnalysis.inferTypeForExpression(TypeAnalysis.java:778)
        //     at com.strobel.decompiler.ast.TypeAnalysis.inferCall(TypeAnalysis.java:2669)
        //     at com.strobel.decompiler.ast.TypeAnalysis.doInferTypeForExpression(TypeAnalysis.java:1029)
        //     at com.strobel.decompiler.ast.TypeAnalysis.inferTypeForExpression(TypeAnalysis.java:803)
        //     at com.strobel.decompiler.ast.TypeAnalysis.inferTypeForExpression(TypeAnalysis.java:778)
        //     at com.strobel.decompiler.ast.TypeAnalysis.inferCall(TypeAnalysis.java:2669)
        //     at com.strobel.decompiler.ast.TypeAnalysis.doInferTypeForExpression(TypeAnalysis.java:1029)
        //     at com.strobel.decompiler.ast.TypeAnalysis.inferTypeForExpression(TypeAnalysis.java:803)
        //     at com.strobel.decompiler.ast.TypeAnalysis.inferTypeForExpression(TypeAnalysis.java:778)
        //     at com.strobel.decompiler.ast.TypeAnalysis.inferCall(TypeAnalysis.java:2669)
        //     at com.strobel.decompiler.ast.TypeAnalysis.doInferTypeForExpression(TypeAnalysis.java:1029)
        //     at com.strobel.decompiler.ast.TypeAnalysis.inferTypeForExpression(TypeAnalysis.java:803)
        //     at com.strobel.decompiler.ast.TypeAnalysis.inferTypeForExpression(TypeAnalysis.java:778)
        //     at com.strobel.decompiler.ast.TypeAnalysis.inferCall(TypeAnalysis.java:2669)
        //     at com.strobel.decompiler.ast.TypeAnalysis.doInferTypeForExpression(TypeAnalysis.java:1029)
        //     at com.strobel.decompiler.ast.TypeAnalysis.inferTypeForExpression(TypeAnalysis.java:803)
        //     at com.strobel.decompiler.ast.TypeAnalysis.inferTypeForExpression(TypeAnalysis.java:778)
        //     at com.strobel.decompiler.ast.TypeAnalysis.inferCall(TypeAnalysis.java:2669)
        //     at com.strobel.decompiler.ast.TypeAnalysis.doInferTypeForExpression(TypeAnalysis.java:1029)
        //     at com.strobel.decompiler.ast.TypeAnalysis.inferTypeForExpression(TypeAnalysis.java:803)
        //     at com.strobel.decompiler.ast.TypeAnalysis.inferTypeForExpression(TypeAnalysis.java:778)
        //     at com.strobel.decompiler.ast.TypeAnalysis.inferCall(TypeAnalysis.java:2669)
        //     at com.strobel.decompiler.ast.TypeAnalysis.doInferTypeForExpression(TypeAnalysis.java:1029)
        //     at com.strobel.decompiler.ast.TypeAnalysis.inferTypeForExpression(TypeAnalysis.java:803)
        //     at com.strobel.decompiler.ast.TypeAnalysis.inferTypeForExpression(TypeAnalysis.java:778)
        //     at com.strobel.decompiler.ast.TypeAnalysis.inferCall(TypeAnalysis.java:2669)
        //     at com.strobel.decompiler.ast.TypeAnalysis.doInferTypeForExpression(TypeAnalysis.java:1029)
        //     at com.strobel.decompiler.ast.TypeAnalysis.inferTypeForExpression(TypeAnalysis.java:803)
        //     at com.strobel.decompiler.ast.TypeAnalysis.inferTypeForExpression(TypeAnalysis.java:778)
        //     at com.strobel.decompiler.ast.TypeAnalysis.inferCall(TypeAnalysis.java:2669)
        //     at com.strobel.decompiler.ast.TypeAnalysis.doInferTypeForExpression(TypeAnalysis.java:1029)
        //     at com.strobel.decompiler.ast.TypeAnalysis.inferTypeForExpression(TypeAnalysis.java:803)
        //     at com.strobel.decompiler.ast.TypeAnalysis.inferTypeForExpression(TypeAnalysis.java:778)
        //     at com.strobel.decompiler.ast.TypeAnalysis.inferCall(TypeAnalysis.java:2669)
        //     at com.strobel.decompiler.ast.TypeAnalysis.doInferTypeForExpression(TypeAnalysis.java:1029)
        //     at com.strobel.decompiler.ast.TypeAnalysis.inferTypeForExpression(TypeAnalysis.java:803)
        //     at com.strobel.decompiler.ast.TypeAnalysis.inferTypeForExpression(TypeAnalysis.java:778)
        //     at com.strobel.decompiler.ast.TypeAnalysis.inferCall(TypeAnalysis.java:2669)
        //     at com.strobel.decompiler.ast.TypeAnalysis.doInferTypeForExpression(TypeAnalysis.java:1029)
        //     at com.strobel.decompiler.ast.TypeAnalysis.inferTypeForExpression(TypeAnalysis.java:803)
        //     at com.strobel.decompiler.ast.TypeAnalysis.inferTypeForExpression(TypeAnalysis.java:778)
        //     at com.strobel.decompiler.ast.TypeAnalysis.inferCall(TypeAnalysis.java:2669)
        //     at com.strobel.decompiler.ast.TypeAnalysis.doInferTypeForExpression(TypeAnalysis.java:1029)
        //     at com.strobel.decompiler.ast.TypeAnalysis.inferTypeForExpression(TypeAnalysis.java:803)
        //     at com.strobel.decompiler.ast.TypeAnalysis.inferTypeForExpression(TypeAnalysis.java:778)
        //     at com.strobel.decompiler.ast.TypeAnalysis.inferCall(TypeAnalysis.java:2669)
        //     at com.strobel.decompiler.ast.TypeAnalysis.doInferTypeForExpression(TypeAnalysis.java:1029)
        //     at com.strobel.decompiler.ast.TypeAnalysis.inferTypeForExpression(TypeAnalysis.java:803)
        //     at com.strobel.decompiler.ast.TypeAnalysis.inferTypeForExpression(TypeAnalysis.java:778)
        //     at com.strobel.decompiler.ast.TypeAnalysis.inferCall(TypeAnalysis.java:2669)
        //     at com.strobel.decompiler.ast.TypeAnalysis.doInferTypeForExpression(TypeAnalysis.java:1029)
        //     at com.strobel.decompiler.ast.TypeAnalysis.inferTypeForExpression(TypeAnalysis.java:803)
        //     at com.strobel.decompiler.ast.TypeAnalysis.inferTypeForExpression(TypeAnalysis.java:778)
        //     at com.strobel.decompiler.ast.TypeAnalysis.inferCall(TypeAnalysis.java:2669)
        //     at com.strobel.decompiler.ast.TypeAnalysis.doInferTypeForExpression(TypeAnalysis.java:1029)
        //     at com.strobel.decompiler.ast.TypeAnalysis.inferTypeForExpression(TypeAnalysis.java:803)
        //     at com.strobel.decompiler.ast.TypeAnalysis.inferTypeForExpression(TypeAnalysis.java:778)
        //     at com.strobel.decompiler.ast.TypeAnalysis.inferCall(TypeAnalysis.java:2669)
        //     at com.strobel.decompiler.ast.TypeAnalysis.doInferTypeForExpression(TypeAnalysis.java:1029)
        //     at com.strobel.decompiler.ast.TypeAnalysis.inferTypeForExpression(TypeAnalysis.java:803)
        //     at com.strobel.decompiler.ast.TypeAnalysis.inferTypeForExpression(TypeAnalysis.java:778)
        //     at com.strobel.decompiler.ast.TypeAnalysis.inferCall(TypeAnalysis.java:2669)
        //     at com.strobel.decompiler.ast.TypeAnalysis.doInferTypeForExpression(TypeAnalysis.java:1029)
        //     at com.strobel.decompiler.ast.TypeAnalysis.inferTypeForExpression(TypeAnalysis.java:803)
        //     at com.strobel.decompiler.ast.TypeAnalysis.inferTypeForExpression(TypeAnalysis.java:770)
        //     at com.strobel.decompiler.ast.TypeAnalysis.inferTypeForExpression(TypeAnalysis.java:766)
        //     at com.strobel.decompiler.ast.TypeAnalysis.inferCall(TypeAnalysis.java:2463)
        //     at com.strobel.decompiler.ast.TypeAnalysis.doInferTypeForExpression(TypeAnalysis.java:1029)
        //     at com.strobel.decompiler.ast.TypeAnalysis.inferTypeForExpression(TypeAnalysis.java:803)
        //     at com.strobel.decompiler.ast.TypeAnalysis.inferTypeForExpression(TypeAnalysis.java:770)
        //     at com.strobel.decompiler.ast.TypeAnalysis.inferTypeForExpression(TypeAnalysis.java:766)
        //     at com.strobel.decompiler.ast.TypeAnalysis.inferCall(TypeAnalysis.java:2463)
        //     at com.strobel.decompiler.ast.TypeAnalysis.doInferTypeForExpression(TypeAnalysis.java:1029)
        //     at com.strobel.decompiler.ast.TypeAnalysis.inferTypeForExpression(TypeAnalysis.java:803)
        //     at com.strobel.decompiler.ast.TypeAnalysis.inferTypeForExpression(TypeAnalysis.java:770)
        //     at com.strobel.decompiler.ast.TypeAnalysis.inferTypeForExpression(TypeAnalysis.java:766)
        //     at com.strobel.decompiler.ast.TypeAnalysis.doInferTypeForExpression(TypeAnalysis.java:1072)
        //     at com.strobel.decompiler.ast.TypeAnalysis.inferTypeForExpression(TypeAnalysis.java:803)
        //     at com.strobel.decompiler.ast.TypeAnalysis.runInference(TypeAnalysis.java:672)
        //     at com.strobel.decompiler.ast.TypeAnalysis.runInference(TypeAnalysis.java:655)
        //     at com.strobel.decompiler.ast.TypeAnalysis.runInference(TypeAnalysis.java:365)
        //     at com.strobel.decompiler.ast.TypeAnalysis.run(TypeAnalysis.java:96)
        //     at com.strobel.decompiler.ast.AstOptimizer.optimize(AstOptimizer.java:344)
        //     at com.strobel.decompiler.ast.AstOptimizer.optimize(AstOptimizer.java:42)
        //     at com.strobel.decompiler.languages.java.ast.AstMethodBodyBuilder.createMethodBody(AstMethodBodyBuilder.java:214)
        //     at com.strobel.decompiler.languages.java.ast.AstMethodBodyBuilder.createMethodBody(AstMethodBodyBuilder.java:99)
        //     at com.strobel.decompiler.languages.java.ast.AstBuilder.createMethodBody(AstBuilder.java:782)
        //     at com.strobel.decompiler.languages.java.ast.AstBuilder.createMethod(AstBuilder.java:675)
        //     at com.strobel.decompiler.languages.java.ast.AstBuilder.addTypeMembers(AstBuilder.java:552)
        //     at com.strobel.decompiler.languages.java.ast.AstBuilder.createTypeCore(AstBuilder.java:519)
        //     at com.strobel.decompiler.languages.java.ast.AstBuilder.createTypeNoCache(AstBuilder.java:161)
        //     at com.strobel.decompiler.languages.java.ast.AstBuilder.createType(AstBuilder.java:150)
        //     at com.strobel.decompiler.languages.java.ast.AstBuilder.addType(AstBuilder.java:125)
        //     at cuchaz.enigma.source.procyon.ProcyonDecompiler.getSource(ProcyonDecompiler.java:75)
        //     at cuchaz.enigma.EnigmaProject$JarExport.decompileClass(EnigmaProject.java:270)
        //     at cuchaz.enigma.EnigmaProject$JarExport.lambda$decompileStream$1(EnigmaProject.java:246)
        //     at java.base/java.util.stream.ReferencePipeline$3$1.accept(ReferencePipeline.java:195)
        //     at java.base/java.util.ArrayList$ArrayListSpliterator.forEachRemaining(ArrayList.java:1624)
        //     at java.base/java.util.stream.AbstractPipeline.copyInto(AbstractPipeline.java:484)
        //     at java.base/java.util.stream.ForEachOps$ForEachTask.compute(ForEachOps.java:290)
        //     at java.base/java.util.concurrent.CountedCompleter.exec(CountedCompleter.java:746)
        //     at java.base/java.util.concurrent.ForkJoinTask.doExec(ForkJoinTask.java:290)
        //     at java.base/java.util.concurrent.ForkJoinPool$WorkQueue.topLevelExec(ForkJoinPool.java:1016)
        //     at java.base/java.util.concurrent.ForkJoinPool.scan(ForkJoinPool.java:1665)
        //     at java.base/java.util.concurrent.ForkJoinPool.runWorker(ForkJoinPool.java:1598)
        //     at java.base/java.util.concurrent.ForkJoinWorkerThread.run(ForkJoinWorkerThread.java:177)
        // 
        throw new IllegalStateException("An error occurred while decompiling this method.");
    }
}
