package it.unimi.dsi.fastutil.chars;

import java.io.ObjectInputStream;
import java.io.IOException;
import java.io.ObjectOutputStream;
import java.util.NoSuchElementException;
import java.util.Iterator;
import java.util.SortedSet;
import java.util.Collection;
import java.util.Comparator;
import java.io.Serializable;

public class CharRBTreeSet extends AbstractCharSortedSet implements Serializable, Cloneable, CharSortedSet {
    protected transient Entry tree;
    protected int count;
    protected transient Entry firstEntry;
    protected transient Entry lastEntry;
    protected Comparator<? super Character> storedComparator;
    protected transient CharComparator actualComparator;
    private static final long serialVersionUID = -7046029254386353130L;
    private transient boolean[] dirPath;
    private transient Entry[] nodePath;
    
    public CharRBTreeSet() {
        this.allocatePaths();
        this.tree = null;
        this.count = 0;
    }
    
    private void setActualComparator() {
        this.actualComparator = CharComparators.asCharComparator(this.storedComparator);
    }
    
    public CharRBTreeSet(final Comparator<? super Character> c) {
        this();
        this.storedComparator = c;
        this.setActualComparator();
    }
    
    public CharRBTreeSet(final Collection<? extends Character> c) {
        this();
        this.addAll((Collection)c);
    }
    
    public CharRBTreeSet(final SortedSet<Character> s) {
        this(s.comparator());
        this.addAll((Collection)s);
    }
    
    public CharRBTreeSet(final CharCollection c) {
        this();
        this.addAll(c);
    }
    
    public CharRBTreeSet(final CharSortedSet s) {
        this(s.comparator());
        this.addAll(s);
    }
    
    public CharRBTreeSet(final CharIterator i) {
        this.allocatePaths();
        while (i.hasNext()) {
            this.add(i.nextChar());
        }
    }
    
    public CharRBTreeSet(final Iterator<?> i) {
        this(CharIterators.asCharIterator(i));
    }
    
    public CharRBTreeSet(final char[] a, final int offset, final int length, final Comparator<? super Character> c) {
        this(c);
        CharArrays.ensureOffsetLength(a, offset, length);
        for (int i = 0; i < length; ++i) {
            this.add(a[offset + i]);
        }
    }
    
    public CharRBTreeSet(final char[] a, final int offset, final int length) {
        this(a, offset, length, null);
    }
    
    public CharRBTreeSet(final char[] a) {
        this();
        int i = a.length;
        while (i-- != 0) {
            this.add(a[i]);
        }
    }
    
    public CharRBTreeSet(final char[] a, final Comparator<? super Character> c) {
        this(c);
        int i = a.length;
        while (i-- != 0) {
            this.add(a[i]);
        }
    }
    
    final int compare(final char k1, final char k2) {
        return (this.actualComparator == null) ? Character.compare(k1, k2) : this.actualComparator.compare(k1, k2);
    }
    
    private Entry findKey(final char k) {
        Entry e;
        int cmp;
        for (e = this.tree; e != null && (cmp = this.compare(k, e.key)) != 0; e = ((cmp < 0) ? e.left() : e.right())) {}
        return e;
    }
    
    final Entry locateKey(final char k) {
        Entry e = this.tree;
        Entry last = this.tree;
        int cmp;
        for (cmp = 0; e != null && (cmp = this.compare(k, e.key)) != 0; e = ((cmp < 0) ? e.left() : e.right())) {
            last = e;
        }
        return (cmp == 0) ? e : last;
    }
    
    private void allocatePaths() {
        this.dirPath = new boolean[64];
        this.nodePath = new Entry[64];
    }
    
    public boolean add(final char k) {
        int maxDepth = 0;
        Label_0876: {
            if (this.tree != null) {
                Entry p = this.tree;
                int i = 0;
                int cmp;
                while ((cmp = this.compare(k, p.key)) != 0) {
                    this.nodePath[i] = p;
                    final boolean[] dirPath = this.dirPath;
                    final int n = i++;
                    final boolean b = cmp > 0;
                    dirPath[n] = b;
                    if (b) {
                        if (!p.succ()) {
                            p = p.right;
                            continue;
                        }
                        ++this.count;
                        final Entry e = new Entry(k);
                        if (p.right == null) {
                            this.lastEntry = e;
                        }
                        e.left = p;
                        e.right = p.right;
                        p.right(e);
                    }
                    else {
                        if (!p.pred()) {
                            p = p.left;
                            continue;
                        }
                        ++this.count;
                        final Entry e = new Entry(k);
                        if (p.left == null) {
                            this.firstEntry = e;
                        }
                        e.right = p;
                        e.left = p.left;
                        p.left(e);
                    }
                    maxDepth = i--;
                    while (i > 0 && !this.nodePath[i].black()) {
                        if (!this.dirPath[i - 1]) {
                            Entry y = this.nodePath[i - 1].right;
                            if (!this.nodePath[i - 1].succ() && !y.black()) {
                                this.nodePath[i].black(true);
                                y.black(true);
                                this.nodePath[i - 1].black(false);
                                i -= 2;
                            }
                            else {
                                if (!this.dirPath[i]) {
                                    y = this.nodePath[i];
                                }
                                else {
                                    final Entry x = this.nodePath[i];
                                    y = x.right;
                                    x.right = y.left;
                                    y.left = x;
                                    this.nodePath[i - 1].left = y;
                                    if (y.pred()) {
                                        y.pred(false);
                                        x.succ(y);
                                    }
                                }
                                final Entry x = this.nodePath[i - 1];
                                x.black(false);
                                y.black(true);
                                x.left = y.right;
                                y.right = x;
                                if (i < 2) {
                                    this.tree = y;
                                }
                                else if (this.dirPath[i - 2]) {
                                    this.nodePath[i - 2].right = y;
                                }
                                else {
                                    this.nodePath[i - 2].left = y;
                                }
                                if (y.succ()) {
                                    y.succ(false);
                                    x.pred(y);
                                    break;
                                }
                                break;
                            }
                        }
                        else {
                            Entry y = this.nodePath[i - 1].left;
                            if (!this.nodePath[i - 1].pred() && !y.black()) {
                                this.nodePath[i].black(true);
                                y.black(true);
                                this.nodePath[i - 1].black(false);
                                i -= 2;
                            }
                            else {
                                if (this.dirPath[i]) {
                                    y = this.nodePath[i];
                                }
                                else {
                                    final Entry x = this.nodePath[i];
                                    y = x.left;
                                    x.left = y.right;
                                    y.right = x;
                                    this.nodePath[i - 1].right = y;
                                    if (y.succ()) {
                                        y.succ(false);
                                        x.pred(y);
                                    }
                                }
                                final Entry x = this.nodePath[i - 1];
                                x.black(false);
                                y.black(true);
                                x.right = y.left;
                                y.left = x;
                                if (i < 2) {
                                    this.tree = y;
                                }
                                else if (this.dirPath[i - 2]) {
                                    this.nodePath[i - 2].right = y;
                                }
                                else {
                                    this.nodePath[i - 2].left = y;
                                }
                                if (y.pred()) {
                                    y.pred(false);
                                    x.succ(y);
                                    break;
                                }
                                break;
                            }
                        }
                    }
                    break Label_0876;
                }
                while (i-- != 0) {
                    this.nodePath[i] = null;
                }
                return false;
            }
            ++this.count;
            final Entry tree = new Entry(k);
            this.firstEntry = tree;
            this.lastEntry = tree;
            this.tree = tree;
        }
        this.tree.black(true);
        while (maxDepth-- != 0) {
            this.nodePath[maxDepth] = null;
        }
        return true;
    }
    
    public boolean remove(final char k) {
        if (this.tree == null) {
            return false;
        }
        Entry p = this.tree;
        int i = 0;
        final char kk = k;
        int cmp;
        while ((cmp = this.compare(kk, p.key)) != 0) {
            this.dirPath[i] = (cmp > 0);
            this.nodePath[i] = p;
            if (this.dirPath[i++]) {
                if ((p = p.right()) == null) {
                    while (i-- != 0) {
                        this.nodePath[i] = null;
                    }
                    return false;
                }
                continue;
            }
            else {
                if ((p = p.left()) == null) {
                    while (i-- != 0) {
                        this.nodePath[i] = null;
                    }
                    return false;
                }
                continue;
            }
        }
        if (p.left == null) {
            this.firstEntry = p.next();
        }
        if (p.right == null) {
            this.lastEntry = p.prev();
        }
        if (p.succ()) {
            if (p.pred()) {
                if (i == 0) {
                    this.tree = p.left;
                }
                else if (this.dirPath[i - 1]) {
                    this.nodePath[i - 1].succ(p.right);
                }
                else {
                    this.nodePath[i - 1].pred(p.left);
                }
            }
            else {
                p.prev().right = p.right;
                if (i == 0) {
                    this.tree = p.left;
                }
                else if (this.dirPath[i - 1]) {
                    this.nodePath[i - 1].right = p.left;
                }
                else {
                    this.nodePath[i - 1].left = p.left;
                }
            }
        }
        else {
            Entry r = p.right;
            if (r.pred()) {
                r.left = p.left;
                r.pred(p.pred());
                if (!r.pred()) {
                    r.prev().right = r;
                }
                if (i == 0) {
                    this.tree = r;
                }
                else if (this.dirPath[i - 1]) {
                    this.nodePath[i - 1].right = r;
                }
                else {
                    this.nodePath[i - 1].left = r;
                }
                final boolean color = r.black();
                r.black(p.black());
                p.black(color);
                this.dirPath[i] = true;
                this.nodePath[i++] = r;
            }
            else {
                final int j = i++;
                Entry s;
                while (true) {
                    this.dirPath[i] = false;
                    this.nodePath[i++] = r;
                    s = r.left;
                    if (s.pred()) {
                        break;
                    }
                    r = s;
                }
                this.dirPath[j] = true;
                this.nodePath[j] = s;
                if (s.succ()) {
                    r.pred(s);
                }
                else {
                    r.left = s.right;
                }
                s.left = p.left;
                if (!p.pred()) {
                    (p.prev().right = s).pred(false);
                }
                s.right(p.right);
                final boolean color = s.black();
                s.black(p.black());
                p.black(color);
                if (j == 0) {
                    this.tree = s;
                }
                else if (this.dirPath[j - 1]) {
                    this.nodePath[j - 1].right = s;
                }
                else {
                    this.nodePath[j - 1].left = s;
                }
            }
        }
        int maxDepth = i;
        if (p.black()) {
            while (i > 0) {
                if ((this.dirPath[i - 1] && !this.nodePath[i - 1].succ()) || (!this.dirPath[i - 1] && !this.nodePath[i - 1].pred())) {
                    final Entry x = this.dirPath[i - 1] ? this.nodePath[i - 1].right : this.nodePath[i - 1].left;
                    if (!x.black()) {
                        x.black(true);
                        break;
                    }
                }
                if (!this.dirPath[i - 1]) {
                    Entry w = this.nodePath[i - 1].right;
                    if (!w.black()) {
                        w.black(true);
                        this.nodePath[i - 1].black(false);
                        this.nodePath[i - 1].right = w.left;
                        w.left = this.nodePath[i - 1];
                        if (i < 2) {
                            this.tree = w;
                        }
                        else if (this.dirPath[i - 2]) {
                            this.nodePath[i - 2].right = w;
                        }
                        else {
                            this.nodePath[i - 2].left = w;
                        }
                        this.nodePath[i] = this.nodePath[i - 1];
                        this.dirPath[i] = false;
                        this.nodePath[i - 1] = w;
                        if (maxDepth == i++) {
                            ++maxDepth;
                        }
                        w = this.nodePath[i - 1].right;
                    }
                    if ((w.pred() || w.left.black()) && (w.succ() || w.right.black())) {
                        w.black(false);
                    }
                    else {
                        if (w.succ() || w.right.black()) {
                            final Entry y = w.left;
                            y.black(true);
                            w.black(false);
                            w.left = y.right;
                            y.right = w;
                            final Entry entry = this.nodePath[i - 1];
                            final Entry right = y;
                            entry.right = right;
                            w = right;
                            if (w.succ()) {
                                w.succ(false);
                                w.right.pred(w);
                            }
                        }
                        w.black(this.nodePath[i - 1].black());
                        this.nodePath[i - 1].black(true);
                        w.right.black(true);
                        this.nodePath[i - 1].right = w.left;
                        w.left = this.nodePath[i - 1];
                        if (i < 2) {
                            this.tree = w;
                        }
                        else if (this.dirPath[i - 2]) {
                            this.nodePath[i - 2].right = w;
                        }
                        else {
                            this.nodePath[i - 2].left = w;
                        }
                        if (w.pred()) {
                            w.pred(false);
                            this.nodePath[i - 1].succ(w);
                            break;
                        }
                        break;
                    }
                }
                else {
                    Entry w = this.nodePath[i - 1].left;
                    if (!w.black()) {
                        w.black(true);
                        this.nodePath[i - 1].black(false);
                        this.nodePath[i - 1].left = w.right;
                        w.right = this.nodePath[i - 1];
                        if (i < 2) {
                            this.tree = w;
                        }
                        else if (this.dirPath[i - 2]) {
                            this.nodePath[i - 2].right = w;
                        }
                        else {
                            this.nodePath[i - 2].left = w;
                        }
                        this.nodePath[i] = this.nodePath[i - 1];
                        this.dirPath[i] = true;
                        this.nodePath[i - 1] = w;
                        if (maxDepth == i++) {
                            ++maxDepth;
                        }
                        w = this.nodePath[i - 1].left;
                    }
                    if ((w.pred() || w.left.black()) && (w.succ() || w.right.black())) {
                        w.black(false);
                    }
                    else {
                        if (w.pred() || w.left.black()) {
                            final Entry y = w.right;
                            y.black(true);
                            w.black(false);
                            w.right = y.left;
                            y.left = w;
                            final Entry entry2 = this.nodePath[i - 1];
                            final Entry left = y;
                            entry2.left = left;
                            w = left;
                            if (w.pred()) {
                                w.pred(false);
                                w.left.succ(w);
                            }
                        }
                        w.black(this.nodePath[i - 1].black());
                        this.nodePath[i - 1].black(true);
                        w.left.black(true);
                        this.nodePath[i - 1].left = w.right;
                        w.right = this.nodePath[i - 1];
                        if (i < 2) {
                            this.tree = w;
                        }
                        else if (this.dirPath[i - 2]) {
                            this.nodePath[i - 2].right = w;
                        }
                        else {
                            this.nodePath[i - 2].left = w;
                        }
                        if (w.succ()) {
                            w.succ(false);
                            this.nodePath[i - 1].pred(w);
                            break;
                        }
                        break;
                    }
                }
                --i;
            }
            if (this.tree != null) {
                this.tree.black(true);
            }
        }
        --this.count;
        while (maxDepth-- != 0) {
            this.nodePath[maxDepth] = null;
        }
        return true;
    }
    
    public boolean contains(final char k) {
        return this.findKey(k) != null;
    }
    
    public void clear() {
        this.count = 0;
        this.tree = null;
        final Entry entry = null;
        this.lastEntry = entry;
        this.firstEntry = entry;
    }
    
    public int size() {
        return this.count;
    }
    
    public boolean isEmpty() {
        return this.count == 0;
    }
    
    public char firstChar() {
        if (this.tree == null) {
            throw new NoSuchElementException();
        }
        return this.firstEntry.key;
    }
    
    public char lastChar() {
        if (this.tree == null) {
            throw new NoSuchElementException();
        }
        return this.lastEntry.key;
    }
    
    @Override
    public CharBidirectionalIterator iterator() {
        return new SetIterator();
    }
    
    public CharBidirectionalIterator iterator(final char from) {
        return new SetIterator(from);
    }
    
    public CharComparator comparator() {
        return this.actualComparator;
    }
    
    public CharSortedSet headSet(final char to) {
        return new Subset('\0', true, to, false);
    }
    
    public CharSortedSet tailSet(final char from) {
        return new Subset(from, false, '\0', true);
    }
    
    public CharSortedSet subSet(final char from, final char to) {
        return new Subset(from, false, to, false);
    }
    
    public Object clone() {
        CharRBTreeSet c;
        try {
            c = (CharRBTreeSet)super.clone();
        }
        catch (CloneNotSupportedException cantHappen) {
            throw new InternalError();
        }
        c.allocatePaths();
        if (this.count != 0) {
            final Entry rp = new Entry();
            final Entry rq = new Entry();
            Entry p = rp;
            rp.left(this.tree);
            Entry q = rq;
            rq.pred(null);
        Block_4:
            while (true) {
                if (!p.pred()) {
                    final Entry e = p.left.clone();
                    e.pred(q.left);
                    e.succ(q);
                    q.left(e);
                    p = p.left;
                    q = q.left;
                }
                else {
                    while (p.succ()) {
                        p = p.right;
                        if (p == null) {
                            break Block_4;
                        }
                        q = q.right;
                    }
                    p = p.right;
                    q = q.right;
                }
                if (!p.succ()) {
                    final Entry e = p.right.clone();
                    e.succ(q.right);
                    e.pred(q);
                    q.right(e);
                }
            }
            q.right = null;
            c.tree = rq.left;
            c.firstEntry = c.tree;
            while (c.firstEntry.left != null) {
                c.firstEntry = c.firstEntry.left;
            }
            c.lastEntry = c.tree;
            while (c.lastEntry.right != null) {
                c.lastEntry = c.lastEntry.right;
            }
            return c;
        }
        return c;
    }
    
    private void writeObject(final ObjectOutputStream s) throws IOException {
        int n = this.count;
        final SetIterator i = new SetIterator();
        s.defaultWriteObject();
        while (n-- != 0) {
            s.writeChar((int)i.nextChar());
        }
    }
    
    private Entry readTree(final ObjectInputStream s, final int n, final Entry pred, final Entry succ) throws IOException, ClassNotFoundException {
        if (n == 1) {
            final Entry top = new Entry(s.readChar());
            top.pred(pred);
            top.succ(succ);
            top.black(true);
            return top;
        }
        if (n == 2) {
            final Entry top = new Entry(s.readChar());
            top.black(true);
            top.right(new Entry(s.readChar()));
            top.right.pred(top);
            top.pred(pred);
            top.right.succ(succ);
            return top;
        }
        final int rightN = n / 2;
        final int leftN = n - rightN - 1;
        final Entry top2 = new Entry();
        top2.left(this.readTree(s, leftN, pred, top2));
        top2.key = s.readChar();
        top2.black(true);
        top2.right(this.readTree(s, rightN, top2, succ));
        if (n + 2 == (n + 2 & -(n + 2))) {
            top2.right.black(false);
        }
        return top2;
    }
    
    private void readObject(final ObjectInputStream s) throws IOException, ClassNotFoundException {
        s.defaultReadObject();
        this.setActualComparator();
        this.allocatePaths();
        if (this.count != 0) {
            this.tree = this.readTree(s, this.count, null, null);
            Entry e;
            for (e = this.tree; e.left() != null; e = e.left()) {}
            this.firstEntry = e;
            for (e = this.tree; e.right() != null; e = e.right()) {}
            this.lastEntry = e;
        }
    }
    
    private static final class Entry implements Cloneable {
        private static final int BLACK_MASK = 1;
        private static final int SUCC_MASK = Integer.MIN_VALUE;
        private static final int PRED_MASK = 1073741824;
        char key;
        Entry left;
        Entry right;
        int info;
        
        Entry() {
        }
        
        Entry(final char k) {
            this.key = k;
            this.info = -1073741824;
        }
        
        Entry left() {
            return ((this.info & 0x40000000) != 0x0) ? null : this.left;
        }
        
        Entry right() {
            return ((this.info & Integer.MIN_VALUE) != 0x0) ? null : this.right;
        }
        
        boolean pred() {
            return (this.info & 0x40000000) != 0x0;
        }
        
        boolean succ() {
            return (this.info & Integer.MIN_VALUE) != 0x0;
        }
        
        void pred(final boolean pred) {
            if (pred) {
                this.info |= 0x40000000;
            }
            else {
                this.info &= 0xBFFFFFFF;
            }
        }
        
        void succ(final boolean succ) {
            if (succ) {
                this.info |= Integer.MIN_VALUE;
            }
            else {
                this.info &= Integer.MAX_VALUE;
            }
        }
        
        void pred(final Entry pred) {
            this.info |= 0x40000000;
            this.left = pred;
        }
        
        void succ(final Entry succ) {
            this.info |= Integer.MIN_VALUE;
            this.right = succ;
        }
        
        void left(final Entry left) {
            this.info &= 0xBFFFFFFF;
            this.left = left;
        }
        
        void right(final Entry right) {
            this.info &= Integer.MAX_VALUE;
            this.right = right;
        }
        
        boolean black() {
            return (this.info & 0x1) != 0x0;
        }
        
        void black(final boolean black) {
            if (black) {
                this.info |= 0x1;
            }
            else {
                this.info &= 0xFFFFFFFE;
            }
        }
        
        Entry next() {
            Entry next = this.right;
            if ((this.info & Integer.MIN_VALUE) == 0x0) {
                while ((next.info & 0x40000000) == 0x0) {
                    next = next.left;
                }
            }
            return next;
        }
        
        Entry prev() {
            Entry prev = this.left;
            if ((this.info & 0x40000000) == 0x0) {
                while ((prev.info & Integer.MIN_VALUE) == 0x0) {
                    prev = prev.right;
                }
            }
            return prev;
        }
        
        public Entry clone() {
            Entry c;
            try {
                c = (Entry)super.clone();
            }
            catch (CloneNotSupportedException cantHappen) {
                throw new InternalError();
            }
            c.key = this.key;
            c.info = this.info;
            return c;
        }
        
        public boolean equals(final Object o) {
            if (!(o instanceof Entry)) {
                return false;
            }
            final Entry e = (Entry)o;
            return this.key == e.key;
        }
        
        public int hashCode() {
            return this.key;
        }
        
        public String toString() {
            return String.valueOf(this.key);
        }
    }
    
    private class SetIterator implements CharListIterator {
        Entry prev;
        Entry next;
        Entry curr;
        int index;
        
        SetIterator() {
            this.index = 0;
            this.next = CharRBTreeSet.this.firstEntry;
        }
        
        SetIterator(final char k) {
            this.index = 0;
            final Entry locateKey = CharRBTreeSet.this.locateKey(k);
            this.next = locateKey;
            if (locateKey != null) {
                if (CharRBTreeSet.this.compare(this.next.key, k) <= 0) {
                    this.prev = this.next;
                    this.next = this.next.next();
                }
                else {
                    this.prev = this.next.prev();
                }
            }
        }
        
        public boolean hasNext() {
            return this.next != null;
        }
        
        public boolean hasPrevious() {
            return this.prev != null;
        }
        
        void updateNext() {
            this.next = this.next.next();
        }
        
        void updatePrevious() {
            this.prev = this.prev.prev();
        }
        
        public char nextChar() {
            return this.nextEntry().key;
        }
        
        public char previousChar() {
            return this.previousEntry().key;
        }
        
        Entry nextEntry() {
            if (!this.hasNext()) {
                throw new NoSuchElementException();
            }
            final Entry next = this.next;
            this.prev = next;
            this.curr = next;
            ++this.index;
            this.updateNext();
            return this.curr;
        }
        
        Entry previousEntry() {
            if (!this.hasPrevious()) {
                throw new NoSuchElementException();
            }
            final Entry prev = this.prev;
            this.next = prev;
            this.curr = prev;
            --this.index;
            this.updatePrevious();
            return this.curr;
        }
        
        public int nextIndex() {
            return this.index;
        }
        
        public int previousIndex() {
            return this.index - 1;
        }
        
        public void remove() {
            if (this.curr == null) {
                throw new IllegalStateException();
            }
            if (this.curr == this.prev) {
                --this.index;
            }
            final Entry curr = this.curr;
            this.prev = curr;
            this.next = curr;
            this.updatePrevious();
            this.updateNext();
            CharRBTreeSet.this.remove(this.curr.key);
            this.curr = null;
        }
    }
    
    private final class Subset extends AbstractCharSortedSet implements Serializable, CharSortedSet {
        private static final long serialVersionUID = -7046029254386353129L;
        char from;
        char to;
        boolean bottom;
        boolean top;
        final /* synthetic */ CharRBTreeSet this$0;
        
        public Subset(final char from, final boolean bottom, final char to, final boolean top) {
            if (!bottom && !top && CharRBTreeSet.this.compare(from, to) > 0) {
                throw new IllegalArgumentException(new StringBuilder().append("Start element (").append(from).append(") is larger than end element (").append(to).append(")").toString());
            }
            this.from = from;
            this.bottom = bottom;
            this.to = to;
            this.top = top;
        }
        
        public void clear() {
            final SubsetIterator i = new SubsetIterator();
            while (i.hasNext()) {
                i.nextChar();
                i.remove();
            }
        }
        
        final boolean in(final char k) {
            return (this.bottom || CharRBTreeSet.this.compare(k, this.from) >= 0) && (this.top || CharRBTreeSet.this.compare(k, this.to) < 0);
        }
        
        public boolean contains(final char k) {
            return this.in(k) && CharRBTreeSet.this.contains(k);
        }
        
        public boolean add(final char k) {
            if (!this.in(k)) {
                throw new IllegalArgumentException(new StringBuilder().append("Element (").append(k).append(") out of range [").append(this.bottom ? "-" : String.valueOf(this.from)).append(", ").append(this.top ? "-" : String.valueOf(this.to)).append(")").toString());
            }
            return CharRBTreeSet.this.add(k);
        }
        
        public boolean remove(final char k) {
            return this.in(k) && CharRBTreeSet.this.remove(k);
        }
        
        public int size() {
            final SubsetIterator i = new SubsetIterator();
            int n = 0;
            while (i.hasNext()) {
                ++n;
                i.nextChar();
            }
            return n;
        }
        
        public boolean isEmpty() {
            return !new SubsetIterator().hasNext();
        }
        
        public CharComparator comparator() {
            return CharRBTreeSet.this.actualComparator;
        }
        
        @Override
        public CharBidirectionalIterator iterator() {
            return new SubsetIterator();
        }
        
        public CharBidirectionalIterator iterator(final char from) {
            return new SubsetIterator(from);
        }
        
        public CharSortedSet headSet(final char to) {
            if (this.top) {
                return new Subset(this.from, this.bottom, to, false);
            }
            return (CharRBTreeSet.this.compare(to, this.to) < 0) ? new Subset(this.from, this.bottom, to, false) : this;
        }
        
        public CharSortedSet tailSet(final char from) {
            if (this.bottom) {
                return new Subset(from, false, this.to, this.top);
            }
            return (CharRBTreeSet.this.compare(from, this.from) > 0) ? new Subset(from, false, this.to, this.top) : this;
        }
        
        public CharSortedSet subSet(final char from, final char to) {
            // 
            // This method could not be decompiled.
            // 
            // Original Bytecode:
            // 
            //     1: getfield        it/unimi/dsi/fastutil/chars/CharRBTreeSet$Subset.top:Z
            //     4: ifeq            30
            //     7: aload_0         /* this */
            //     8: getfield        it/unimi/dsi/fastutil/chars/CharRBTreeSet$Subset.bottom:Z
            //    11: ifeq            30
            //    14: new             Lit/unimi/dsi/fastutil/chars/CharRBTreeSet$Subset;
            //    17: dup            
            //    18: aload_0         /* this */
            //    19: getfield        it/unimi/dsi/fastutil/chars/CharRBTreeSet$Subset.this$0:Lit/unimi/dsi/fastutil/chars/CharRBTreeSet;
            //    22: iload_1         /* from */
            //    23: iconst_0       
            //    24: iload_2         /* to */
            //    25: iconst_0       
            //    26: invokespecial   it/unimi/dsi/fastutil/chars/CharRBTreeSet$Subset.<init>:(Lit/unimi/dsi/fastutil/chars/CharRBTreeSet;CZCZ)V
            //    29: areturn        
            //    30: aload_0         /* this */
            //    31: getfield        it/unimi/dsi/fastutil/chars/CharRBTreeSet$Subset.top:Z
            //    34: ifne            61
            //    37: aload_0         /* this */
            //    38: getfield        it/unimi/dsi/fastutil/chars/CharRBTreeSet$Subset.this$0:Lit/unimi/dsi/fastutil/chars/CharRBTreeSet;
            //    41: iload_2         /* to */
            //    42: aload_0         /* this */
            //    43: getfield        it/unimi/dsi/fastutil/chars/CharRBTreeSet$Subset.to:C
            //    46: invokevirtual   it/unimi/dsi/fastutil/chars/CharRBTreeSet.compare:(CC)I
            //    49: ifge            56
            //    52: iload_2         /* to */
            //    53: goto            60
            //    56: aload_0         /* this */
            //    57: getfield        it/unimi/dsi/fastutil/chars/CharRBTreeSet$Subset.to:C
            //    60: istore_2        /* to */
            //    61: aload_0         /* this */
            //    62: getfield        it/unimi/dsi/fastutil/chars/CharRBTreeSet$Subset.bottom:Z
            //    65: ifne            92
            //    68: aload_0         /* this */
            //    69: getfield        it/unimi/dsi/fastutil/chars/CharRBTreeSet$Subset.this$0:Lit/unimi/dsi/fastutil/chars/CharRBTreeSet;
            //    72: iload_1         /* from */
            //    73: aload_0         /* this */
            //    74: getfield        it/unimi/dsi/fastutil/chars/CharRBTreeSet$Subset.from:C
            //    77: invokevirtual   it/unimi/dsi/fastutil/chars/CharRBTreeSet.compare:(CC)I
            //    80: ifle            87
            //    83: iload_1         /* from */
            //    84: goto            91
            //    87: aload_0         /* this */
            //    88: getfield        it/unimi/dsi/fastutil/chars/CharRBTreeSet$Subset.from:C
            //    91: istore_1        /* from */
            //    92: aload_0         /* this */
            //    93: getfield        it/unimi/dsi/fastutil/chars/CharRBTreeSet$Subset.top:Z
            //    96: ifne            124
            //    99: aload_0         /* this */
            //   100: getfield        it/unimi/dsi/fastutil/chars/CharRBTreeSet$Subset.bottom:Z
            //   103: ifne            124
            //   106: iload_1         /* from */
            //   107: aload_0         /* this */
            //   108: getfield        it/unimi/dsi/fastutil/chars/CharRBTreeSet$Subset.from:C
            //   111: if_icmpne       124
            //   114: iload_2         /* to */
            //   115: aload_0         /* this */
            //   116: getfield        it/unimi/dsi/fastutil/chars/CharRBTreeSet$Subset.to:C
            //   119: if_icmpne       124
            //   122: aload_0         /* this */
            //   123: areturn        
            //   124: new             Lit/unimi/dsi/fastutil/chars/CharRBTreeSet$Subset;
            //   127: dup            
            //   128: aload_0         /* this */
            //   129: getfield        it/unimi/dsi/fastutil/chars/CharRBTreeSet$Subset.this$0:Lit/unimi/dsi/fastutil/chars/CharRBTreeSet;
            //   132: iload_1         /* from */
            //   133: iconst_0       
            //   134: iload_2         /* to */
            //   135: iconst_0       
            //   136: invokespecial   it/unimi/dsi/fastutil/chars/CharRBTreeSet$Subset.<init>:(Lit/unimi/dsi/fastutil/chars/CharRBTreeSet;CZCZ)V
            //   139: areturn        
            //    MethodParameters:
            //  Name  Flags  
            //  ----  -----
            //  from  
            //  to    
            //    StackMapTable: 00 08 1E 19 43 01 00 19 43 01 00 1F
            // 
            // The error that occurred was:
            // 
            // java.lang.ArrayIndexOutOfBoundsException: Array index out of range: 1
            //     at java.base/java.util.Vector.get(Vector.java:749)
            //     at com.strobel.assembler.metadata.MetadataResolver.resolve(MetadataResolver.java:82)
            //     at com.strobel.assembler.metadata.CoreMetadataFactory$UnresolvedType.resolve(CoreMetadataFactory.java:616)
            //     at com.strobel.assembler.metadata.MetadataHelper$9.visitClassType(MetadataHelper.java:2114)
            //     at com.strobel.assembler.metadata.MetadataHelper$9.visitClassType(MetadataHelper.java:2075)
            //     at com.strobel.assembler.metadata.CoreMetadataFactory$UnresolvedType.accept(CoreMetadataFactory.java:577)
            //     at com.strobel.assembler.metadata.DefaultTypeVisitor.visit(DefaultTypeVisitor.java:25)
            //     at com.strobel.assembler.metadata.DefaultTypeVisitor.visit(DefaultTypeVisitor.java:21)
            //     at com.strobel.assembler.metadata.MetadataHelper.getSuperType(MetadataHelper.java:1264)
            //     at com.strobel.assembler.metadata.MetadataHelper$8.visitClassType(MetadataHelper.java:2011)
            //     at com.strobel.assembler.metadata.MetadataHelper$8.visitClassType(MetadataHelper.java:1994)
            //     at com.strobel.assembler.metadata.CoreMetadataFactory$UnresolvedType.accept(CoreMetadataFactory.java:577)
            //     at com.strobel.assembler.metadata.DefaultTypeVisitor.visit(DefaultTypeVisitor.java:25)
            //     at com.strobel.assembler.metadata.MetadataHelper.asSuper(MetadataHelper.java:727)
            //     at com.strobel.assembler.metadata.MetadataHelper$8.visitClassType(MetadataHelper.java:2028)
            //     at com.strobel.assembler.metadata.MetadataHelper$8.visitClassType(MetadataHelper.java:1994)
            //     at com.strobel.assembler.metadata.CoreMetadataFactory$UnresolvedType.accept(CoreMetadataFactory.java:577)
            //     at com.strobel.assembler.metadata.DefaultTypeVisitor.visit(DefaultTypeVisitor.java:25)
            //     at com.strobel.assembler.metadata.MetadataHelper.asSuper(MetadataHelper.java:727)
            //     at com.strobel.assembler.metadata.MetadataHelper$8.visitClassType(MetadataHelper.java:2017)
            //     at com.strobel.assembler.metadata.MetadataHelper$8.visitClassType(MetadataHelper.java:1994)
            //     at com.strobel.assembler.metadata.CoreMetadataFactory$UnresolvedType.accept(CoreMetadataFactory.java:577)
            //     at com.strobel.assembler.metadata.DefaultTypeVisitor.visit(DefaultTypeVisitor.java:25)
            //     at com.strobel.assembler.metadata.MetadataHelper.asSuper(MetadataHelper.java:727)
            //     at com.strobel.assembler.metadata.MetadataHelper$8.visitClassType(MetadataHelper.java:2017)
            //     at com.strobel.assembler.metadata.MetadataHelper$8.visitClassType(MetadataHelper.java:1994)
            //     at com.strobel.assembler.metadata.CoreMetadataFactory$UnresolvedType.accept(CoreMetadataFactory.java:577)
            //     at com.strobel.assembler.metadata.DefaultTypeVisitor.visit(DefaultTypeVisitor.java:25)
            //     at com.strobel.assembler.metadata.MetadataHelper.asSuper(MetadataHelper.java:727)
            //     at com.strobel.assembler.metadata.MetadataHelper$8.visitClassType(MetadataHelper.java:2017)
            //     at com.strobel.assembler.metadata.MetadataHelper$8.visitClassType(MetadataHelper.java:1994)
            //     at com.strobel.assembler.metadata.TypeDefinition.accept(TypeDefinition.java:183)
            //     at com.strobel.assembler.metadata.DefaultTypeVisitor.visit(DefaultTypeVisitor.java:25)
            //     at com.strobel.assembler.metadata.MetadataHelper.asSuper(MetadataHelper.java:727)
            //     at com.strobel.assembler.metadata.MetadataHelper$6.visitClassType(MetadataHelper.java:1853)
            //     at com.strobel.assembler.metadata.MetadataHelper$6.visitClassType(MetadataHelper.java:1815)
            //     at com.strobel.assembler.metadata.TypeDefinition.accept(TypeDefinition.java:183)
            //     at com.strobel.assembler.metadata.DefaultTypeVisitor.visit(DefaultTypeVisitor.java:25)
            //     at com.strobel.assembler.metadata.MetadataHelper.isSubType(MetadataHelper.java:1302)
            //     at com.strobel.assembler.metadata.MetadataHelper.isSubType(MetadataHelper.java:568)
            //     at com.strobel.assembler.metadata.MetadataHelper$11.visitClassType(MetadataHelper.java:2715)
            //     at com.strobel.assembler.metadata.MetadataHelper$11.visitClassType(MetadataHelper.java:2691)
            //     at com.strobel.assembler.metadata.CoreMetadataFactory$UnresolvedType.accept(CoreMetadataFactory.java:577)
            //     at com.strobel.assembler.metadata.DefaultTypeVisitor.visit(DefaultTypeVisitor.java:25)
            //     at com.strobel.assembler.metadata.MetadataHelper.asSubType(MetadataHelper.java:720)
            //     at com.strobel.decompiler.ast.TypeAnalysis.inferInitObject(TypeAnalysis.java:1923)
            //     at com.strobel.decompiler.ast.TypeAnalysis.doInferTypeForExpression(TypeAnalysis.java:1306)
            //     at com.strobel.decompiler.ast.TypeAnalysis.inferTypeForExpression(TypeAnalysis.java:803)
            //     at com.strobel.decompiler.ast.TypeAnalysis.inferTypeForExpression(TypeAnalysis.java:778)
            //     at com.strobel.decompiler.ast.TypeAnalysis.doInferTypeForExpression(TypeAnalysis.java:1656)
            //     at com.strobel.decompiler.ast.TypeAnalysis.inferTypeForExpression(TypeAnalysis.java:803)
            //     at com.strobel.decompiler.ast.TypeAnalysis.runInference(TypeAnalysis.java:672)
            //     at com.strobel.decompiler.ast.TypeAnalysis.runInference(TypeAnalysis.java:655)
            //     at com.strobel.decompiler.ast.TypeAnalysis.runInference(TypeAnalysis.java:365)
            //     at com.strobel.decompiler.ast.TypeAnalysis.run(TypeAnalysis.java:96)
            //     at com.strobel.decompiler.ast.AstOptimizer.optimize(AstOptimizer.java:344)
            //     at com.strobel.decompiler.ast.AstOptimizer.optimize(AstOptimizer.java:42)
            //     at com.strobel.decompiler.languages.java.ast.AstMethodBodyBuilder.createMethodBody(AstMethodBodyBuilder.java:214)
            //     at com.strobel.decompiler.languages.java.ast.AstMethodBodyBuilder.createMethodBody(AstMethodBodyBuilder.java:99)
            //     at com.strobel.decompiler.languages.java.ast.AstBuilder.createMethodBody(AstBuilder.java:782)
            //     at com.strobel.decompiler.languages.java.ast.AstBuilder.createMethod(AstBuilder.java:675)
            //     at com.strobel.decompiler.languages.java.ast.AstBuilder.addTypeMembers(AstBuilder.java:552)
            //     at com.strobel.decompiler.languages.java.ast.AstBuilder.createTypeCore(AstBuilder.java:519)
            //     at com.strobel.decompiler.languages.java.ast.AstBuilder.createTypeNoCache(AstBuilder.java:161)
            //     at com.strobel.decompiler.languages.java.ast.AstBuilder.addTypeMembers(AstBuilder.java:576)
            //     at com.strobel.decompiler.languages.java.ast.AstBuilder.createTypeCore(AstBuilder.java:519)
            //     at com.strobel.decompiler.languages.java.ast.AstBuilder.createTypeNoCache(AstBuilder.java:161)
            //     at com.strobel.decompiler.languages.java.ast.AstBuilder.createType(AstBuilder.java:150)
            //     at com.strobel.decompiler.languages.java.ast.AstBuilder.addType(AstBuilder.java:125)
            //     at cuchaz.enigma.source.procyon.ProcyonDecompiler.getSource(ProcyonDecompiler.java:75)
            //     at cuchaz.enigma.EnigmaProject$JarExport.decompileClass(EnigmaProject.java:270)
            //     at cuchaz.enigma.EnigmaProject$JarExport.lambda$decompileStream$1(EnigmaProject.java:246)
            //     at java.base/java.util.stream.ReferencePipeline$3$1.accept(ReferencePipeline.java:195)
            //     at java.base/java.util.ArrayList$ArrayListSpliterator.forEachRemaining(ArrayList.java:1624)
            //     at java.base/java.util.stream.AbstractPipeline.copyInto(AbstractPipeline.java:484)
            //     at java.base/java.util.stream.ForEachOps$ForEachTask.compute(ForEachOps.java:290)
            //     at java.base/java.util.concurrent.CountedCompleter.exec(CountedCompleter.java:746)
            //     at java.base/java.util.concurrent.ForkJoinTask.doExec(ForkJoinTask.java:290)
            //     at java.base/java.util.concurrent.ForkJoinPool$WorkQueue.topLevelExec(ForkJoinPool.java:1016)
            //     at java.base/java.util.concurrent.ForkJoinPool.scan(ForkJoinPool.java:1665)
            //     at java.base/java.util.concurrent.ForkJoinPool.runWorker(ForkJoinPool.java:1598)
            //     at java.base/java.util.concurrent.ForkJoinWorkerThread.run(ForkJoinWorkerThread.java:177)
            // 
            throw new IllegalStateException("An error occurred while decompiling this method.");
        }
        
        public Entry firstEntry() {
            if (CharRBTreeSet.this.tree == null) {
                return null;
            }
            Entry e;
            if (this.bottom) {
                e = CharRBTreeSet.this.firstEntry;
            }
            else {
                e = CharRBTreeSet.this.locateKey(this.from);
                if (CharRBTreeSet.this.compare(e.key, this.from) < 0) {
                    e = e.next();
                }
            }
            if (e == null || (!this.top && CharRBTreeSet.this.compare(e.key, this.to) >= 0)) {
                return null;
            }
            return e;
        }
        
        public Entry lastEntry() {
            if (CharRBTreeSet.this.tree == null) {
                return null;
            }
            Entry e;
            if (this.top) {
                e = CharRBTreeSet.this.lastEntry;
            }
            else {
                e = CharRBTreeSet.this.locateKey(this.to);
                if (CharRBTreeSet.this.compare(e.key, this.to) >= 0) {
                    e = e.prev();
                }
            }
            if (e == null || (!this.bottom && CharRBTreeSet.this.compare(e.key, this.from) < 0)) {
                return null;
            }
            return e;
        }
        
        public char firstChar() {
            final Entry e = this.firstEntry();
            if (e == null) {
                throw new NoSuchElementException();
            }
            return e.key;
        }
        
        public char lastChar() {
            final Entry e = this.lastEntry();
            if (e == null) {
                throw new NoSuchElementException();
            }
            return e.key;
        }
        
        private final class SubsetIterator extends SetIterator {
            SubsetIterator() {
                Subset.this.this$0.super();
                this.next = Subset.this.firstEntry();
            }
            
            SubsetIterator(final Subset subset, final char k) {
                this(subset);
                if (this.next != null) {
                    if (!subset.bottom && subset.this$0.compare(k, this.next.key) < 0) {
                        this.prev = null;
                    }
                    else {
                        if (!subset.top) {
                            final CharRBTreeSet this$0 = subset.this$0;
                            final Entry lastEntry = subset.lastEntry();
                            this.prev = lastEntry;
                            if (this$0.compare(k, lastEntry.key) >= 0) {
                                this.next = null;
                                return;
                            }
                        }
                        this.next = subset.this$0.locateKey(k);
                        if (subset.this$0.compare(this.next.key, k) <= 0) {
                            this.prev = this.next;
                            this.next = this.next.next();
                        }
                        else {
                            this.prev = this.next.prev();
                        }
                    }
                }
            }
            
            @Override
            void updatePrevious() {
                this.prev = this.prev.prev();
                if (!Subset.this.bottom && this.prev != null && CharRBTreeSet.this.compare(this.prev.key, Subset.this.from) < 0) {
                    this.prev = null;
                }
            }
            
            @Override
            void updateNext() {
                this.next = this.next.next();
                if (!Subset.this.top && this.next != null && CharRBTreeSet.this.compare(this.next.key, Subset.this.to) >= 0) {
                    this.next = null;
                }
            }
        }
    }
}
