package it.unimi.dsi.fastutil.longs;

import java.io.Serializable;
import java.util.Random;
import it.unimi.dsi.fastutil.bytes.ByteBigArrays;
import java.util.Arrays;
import it.unimi.dsi.fastutil.BigArrays;
import it.unimi.dsi.fastutil.Hash;

public final class LongBigArrays {
    public static final long[][] EMPTY_BIG_ARRAY;
    public static final long[][] DEFAULT_EMPTY_BIG_ARRAY;
    public static final Hash.Strategy HASH_STRATEGY;
    private static final int SMALL = 7;
    private static final int MEDIUM = 40;
    private static final int DIGIT_BITS = 8;
    private static final int DIGIT_MASK = 255;
    private static final int DIGITS_PER_ELEMENT = 8;
    
    private LongBigArrays() {
    }
    
    public static long get(final long[][] array, final long index) {
        return array[BigArrays.segment(index)][BigArrays.displacement(index)];
    }
    
    public static void set(final long[][] array, final long index, final long value) {
        array[BigArrays.segment(index)][BigArrays.displacement(index)] = value;
    }
    
    public static void swap(final long[][] array, final long first, final long second) {
        final long t = array[BigArrays.segment(first)][BigArrays.displacement(first)];
        array[BigArrays.segment(first)][BigArrays.displacement(first)] = array[BigArrays.segment(second)][BigArrays.displacement(second)];
        array[BigArrays.segment(second)][BigArrays.displacement(second)] = t;
    }
    
    public static void add(final long[][] array, final long index, final long incr) {
        final long[] array2 = array[BigArrays.segment(index)];
        final int displacement = BigArrays.displacement(index);
        array2[displacement] += incr;
    }
    
    public static void mul(final long[][] array, final long index, final long factor) {
        final long[] array2 = array[BigArrays.segment(index)];
        final int displacement = BigArrays.displacement(index);
        array2[displacement] *= factor;
    }
    
    public static void incr(final long[][] array, final long index) {
        final long[] array2 = array[BigArrays.segment(index)];
        final int displacement = BigArrays.displacement(index);
        ++array2[displacement];
    }
    
    public static void decr(final long[][] array, final long index) {
        final long[] array2 = array[BigArrays.segment(index)];
        final int displacement = BigArrays.displacement(index);
        --array2[displacement];
    }
    
    public static long length(final long[][] array) {
        final int length = array.length;
        return (length == 0) ? 0L : (BigArrays.start(length - 1) + array[length - 1].length);
    }
    
    public static void copy(final long[][] srcArray, final long srcPos, final long[][] destArray, final long destPos, long length) {
        if (destPos <= srcPos) {
            int srcSegment = BigArrays.segment(srcPos);
            int destSegment = BigArrays.segment(destPos);
            int srcDispl = BigArrays.displacement(srcPos);
            int destDispl = BigArrays.displacement(destPos);
            while (length > 0L) {
                final int l = (int)Math.min(length, (long)Math.min(srcArray[srcSegment].length - srcDispl, destArray[destSegment].length - destDispl));
                System.arraycopy(srcArray[srcSegment], srcDispl, destArray[destSegment], destDispl, l);
                if ((srcDispl += l) == 134217728) {
                    srcDispl = 0;
                    ++srcSegment;
                }
                if ((destDispl += l) == 134217728) {
                    destDispl = 0;
                    ++destSegment;
                }
                length -= l;
            }
        }
        else {
            int srcSegment = BigArrays.segment(srcPos + length);
            int destSegment = BigArrays.segment(destPos + length);
            int srcDispl = BigArrays.displacement(srcPos + length);
            int destDispl = BigArrays.displacement(destPos + length);
            while (length > 0L) {
                if (srcDispl == 0) {
                    srcDispl = 134217728;
                    --srcSegment;
                }
                if (destDispl == 0) {
                    destDispl = 134217728;
                    --destSegment;
                }
                final int l = (int)Math.min(length, (long)Math.min(srcDispl, destDispl));
                System.arraycopy(srcArray[srcSegment], srcDispl - l, destArray[destSegment], destDispl - l, l);
                srcDispl -= l;
                destDispl -= l;
                length -= l;
            }
        }
    }
    
    public static void copyFromBig(final long[][] srcArray, final long srcPos, final long[] destArray, int destPos, int length) {
        int srcSegment = BigArrays.segment(srcPos);
        int srcDispl = BigArrays.displacement(srcPos);
        while (length > 0) {
            final int l = Math.min(srcArray[srcSegment].length - srcDispl, length);
            System.arraycopy(srcArray[srcSegment], srcDispl, destArray, destPos, l);
            if ((srcDispl += l) == 134217728) {
                srcDispl = 0;
                ++srcSegment;
            }
            destPos += l;
            length -= l;
        }
    }
    
    public static void copyToBig(final long[] srcArray, int srcPos, final long[][] destArray, final long destPos, long length) {
        int destSegment = BigArrays.segment(destPos);
        int destDispl = BigArrays.displacement(destPos);
        while (length > 0L) {
            final int l = (int)Math.min((long)(destArray[destSegment].length - destDispl), length);
            System.arraycopy(srcArray, srcPos, destArray[destSegment], destDispl, l);
            if ((destDispl += l) == 134217728) {
                destDispl = 0;
                ++destSegment;
            }
            srcPos += l;
            length -= l;
        }
    }
    
    public static long[][] newBigArray(final long length) {
        if (length == 0L) {
            return LongBigArrays.EMPTY_BIG_ARRAY;
        }
        BigArrays.ensureLength(length);
        final int baseLength = (int)(length + 134217727L >>> 27);
        final long[][] base = new long[baseLength][];
        final int residual = (int)(length & 0x7FFFFFFL);
        if (residual != 0) {
            for (int i = 0; i < baseLength - 1; ++i) {
                base[i] = new long[134217728];
            }
            base[baseLength - 1] = new long[residual];
        }
        else {
            for (int i = 0; i < baseLength; ++i) {
                base[i] = new long[134217728];
            }
        }
        return base;
    }
    
    public static long[][] wrap(final long[] array) {
        if (array.length == 0) {
            return LongBigArrays.EMPTY_BIG_ARRAY;
        }
        if (array.length <= 134217728) {
            return new long[][] { array };
        }
        final long[][] bigArray = newBigArray(array.length);
        for (int i = 0; i < bigArray.length; ++i) {
            System.arraycopy(array, (int)BigArrays.start(i), bigArray[i], 0, bigArray[i].length);
        }
        return bigArray;
    }
    
    public static long[][] ensureCapacity(final long[][] array, final long length) {
        return ensureCapacity(array, length, length(array));
    }
    
    public static long[][] forceCapacity(final long[][] array, final long length, final long preserve) {
        BigArrays.ensureLength(length);
        final int valid = array.length - ((array.length != 0 && (array.length <= 0 || array[array.length - 1].length != 134217728)) ? 1 : 0);
        final int baseLength = (int)(length + 134217727L >>> 27);
        final long[][] base = (long[][])Arrays.copyOf((Object[])array, baseLength);
        final int residual = (int)(length & 0x7FFFFFFL);
        if (residual != 0) {
            for (int i = valid; i < baseLength - 1; ++i) {
                base[i] = new long[134217728];
            }
            base[baseLength - 1] = new long[residual];
        }
        else {
            for (int i = valid; i < baseLength; ++i) {
                base[i] = new long[134217728];
            }
        }
        if (preserve - valid * 134217728L > 0L) {
            copy(array, valid * 134217728L, base, valid * 134217728L, preserve - valid * 134217728L);
        }
        return base;
    }
    
    public static long[][] ensureCapacity(final long[][] array, final long length, final long preserve) {
        return (length > length(array)) ? forceCapacity(array, length, preserve) : array;
    }
    
    public static long[][] grow(final long[][] array, final long length) {
        final long oldLength = length(array);
        return (length > oldLength) ? grow(array, length, oldLength) : array;
    }
    
    public static long[][] grow(final long[][] array, final long length, final long preserve) {
        final long oldLength = length(array);
        return (length > oldLength) ? ensureCapacity(array, Math.max(oldLength + (oldLength >> 1), length), preserve) : array;
    }
    
    public static long[][] trim(final long[][] array, final long length) {
        BigArrays.ensureLength(length);
        final long oldLength = length(array);
        if (length >= oldLength) {
            return array;
        }
        final int baseLength = (int)(length + 134217727L >>> 27);
        final long[][] base = (long[][])Arrays.copyOf((Object[])array, baseLength);
        final int residual = (int)(length & 0x7FFFFFFL);
        if (residual != 0) {
            base[baseLength - 1] = LongArrays.trim(base[baseLength - 1], residual);
        }
        return base;
    }
    
    public static long[][] setLength(final long[][] array, final long length) {
        final long oldLength = length(array);
        if (length == oldLength) {
            return array;
        }
        if (length < oldLength) {
            return trim(array, length);
        }
        return ensureCapacity(array, length);
    }
    
    public static long[][] copy(final long[][] array, final long offset, final long length) {
        ensureOffsetLength(array, offset, length);
        final long[][] a = newBigArray(length);
        copy(array, offset, a, 0L, length);
        return a;
    }
    
    public static long[][] copy(final long[][] array) {
        final long[][] base = array.clone();
        int i = base.length;
        while (i-- != 0) {
            base[i] = array[i].clone();
        }
        return base;
    }
    
    public static void fill(final long[][] array, final long value) {
        int i = array.length;
        while (i-- != 0) {
            Arrays.fill(array[i], value);
        }
    }
    
    public static void fill(final long[][] array, final long from, final long to, final long value) {
        final long length = length(array);
        BigArrays.ensureFromTo(length, from, to);
        if (length == 0L) {
            return;
        }
        final int fromSegment = BigArrays.segment(from);
        int toSegment = BigArrays.segment(to);
        final int fromDispl = BigArrays.displacement(from);
        final int toDispl = BigArrays.displacement(to);
        if (fromSegment == toSegment) {
            Arrays.fill(array[fromSegment], fromDispl, toDispl, value);
            return;
        }
        if (toDispl != 0) {
            Arrays.fill(array[toSegment], 0, toDispl, value);
        }
        while (--toSegment > fromSegment) {
            Arrays.fill(array[toSegment], value);
        }
        Arrays.fill(array[fromSegment], fromDispl, 134217728, value);
    }
    
    public static boolean equals(final long[][] a1, final long[][] a2) {
        if (length(a1) != length(a2)) {
            return false;
        }
        int i = a1.length;
        while (i-- != 0) {
            final long[] t = a1[i];
            final long[] u = a2[i];
            int j = t.length;
            while (j-- != 0) {
                if (t[j] != u[j]) {
                    return false;
                }
            }
        }
        return true;
    }
    
    public static String toString(final long[][] a) {
        // 
        // This method could not be decompiled.
        // 
        // Original Bytecode:
        // 
        //     1: ifnonnull       7
        //     4: ldc             "null"
        //     6: areturn        
        //     7: aload_0         /* a */
        //     8: invokestatic    it/unimi/dsi/fastutil/longs/LongBigArrays.length:([[J)J
        //    11: lconst_1       
        //    12: lsub           
        //    13: lstore_1        /* last */
        //    14: lload_1         /* last */
        //    15: ldc2_w          -1
        //    18: lcmp           
        //    19: ifne            25
        //    22: ldc             "[]"
        //    24: areturn        
        //    25: new             Ljava/lang/StringBuilder;
        //    28: dup            
        //    29: invokespecial   java/lang/StringBuilder.<init>:()V
        //    32: astore_3        /* b */
        //    33: aload_3         /* b */
        //    34: bipush          91
        //    36: invokevirtual   java/lang/StringBuilder.append:(C)Ljava/lang/StringBuilder;
        //    39: pop            
        //    40: lconst_0       
        //    41: lstore          i
        //    43: aload_3         /* b */
        //    44: aload_0         /* a */
        //    45: lload           i
        //    47: invokestatic    it/unimi/dsi/fastutil/longs/LongBigArrays.get:([[JJ)J
        //    50: invokestatic    java/lang/String.valueOf:(J)Ljava/lang/String;
        //    53: invokevirtual   java/lang/StringBuilder.append:(Ljava/lang/String;)Ljava/lang/StringBuilder;
        //    56: pop            
        //    57: lload           i
        //    59: lload_1         /* last */
        //    60: lcmp           
        //    61: ifne            74
        //    64: aload_3         /* b */
        //    65: bipush          93
        //    67: invokevirtual   java/lang/StringBuilder.append:(C)Ljava/lang/StringBuilder;
        //    70: invokevirtual   java/lang/StringBuilder.toString:()Ljava/lang/String;
        //    73: areturn        
        //    74: aload_3         /* b */
        //    75: ldc             ", "
        //    77: invokevirtual   java/lang/StringBuilder.append:(Ljava/lang/String;)Ljava/lang/StringBuilder;
        //    80: pop            
        //    81: lload           i
        //    83: lconst_1       
        //    84: ladd           
        //    85: lstore          i
        //    87: goto            43
        //    MethodParameters:
        //  Name  Flags  
        //  ----  -----
        //  a     
        //    StackMapTable: 00 04 07 FC 00 11 04 FD 00 11 07 00 CF 04 1E
        // 
        // The error that occurred was:
        // 
        // java.lang.ArrayIndexOutOfBoundsException: Array index out of range: 10
        //     at java.base/java.util.Vector.get(Vector.java:749)
        //     at com.strobel.assembler.metadata.MetadataResolver.resolve(MetadataResolver.java:82)
        //     at com.strobel.assembler.metadata.CoreMetadataFactory$UnresolvedType.resolve(CoreMetadataFactory.java:616)
        //     at com.strobel.assembler.metadata.MetadataResolver.resolve(MetadataResolver.java:128)
        //     at com.strobel.assembler.metadata.CoreMetadataFactory$UnresolvedType.resolve(CoreMetadataFactory.java:626)
        //     at com.strobel.assembler.metadata.MethodReference.resolve(MethodReference.java:177)
        //     at com.strobel.decompiler.ast.TypeAnalysis.inferCall(TypeAnalysis.java:2438)
        //     at com.strobel.decompiler.ast.TypeAnalysis.doInferTypeForExpression(TypeAnalysis.java:1029)
        //     at com.strobel.decompiler.ast.TypeAnalysis.inferTypeForExpression(TypeAnalysis.java:803)
        //     at com.strobel.decompiler.ast.TypeAnalysis.runInference(TypeAnalysis.java:672)
        //     at com.strobel.decompiler.ast.TypeAnalysis.runInference(TypeAnalysis.java:655)
        //     at com.strobel.decompiler.ast.TypeAnalysis.runInference(TypeAnalysis.java:365)
        //     at com.strobel.decompiler.ast.TypeAnalysis.run(TypeAnalysis.java:96)
        //     at com.strobel.decompiler.ast.AstOptimizer.optimize(AstOptimizer.java:344)
        //     at com.strobel.decompiler.ast.AstOptimizer.optimize(AstOptimizer.java:42)
        //     at com.strobel.decompiler.languages.java.ast.AstMethodBodyBuilder.createMethodBody(AstMethodBodyBuilder.java:214)
        //     at com.strobel.decompiler.languages.java.ast.AstMethodBodyBuilder.createMethodBody(AstMethodBodyBuilder.java:99)
        //     at com.strobel.decompiler.languages.java.ast.AstBuilder.createMethodBody(AstBuilder.java:782)
        //     at com.strobel.decompiler.languages.java.ast.AstBuilder.createMethod(AstBuilder.java:675)
        //     at com.strobel.decompiler.languages.java.ast.AstBuilder.addTypeMembers(AstBuilder.java:552)
        //     at com.strobel.decompiler.languages.java.ast.AstBuilder.createTypeCore(AstBuilder.java:519)
        //     at com.strobel.decompiler.languages.java.ast.AstBuilder.createTypeNoCache(AstBuilder.java:161)
        //     at com.strobel.decompiler.languages.java.ast.AstBuilder.createType(AstBuilder.java:150)
        //     at com.strobel.decompiler.languages.java.ast.AstBuilder.addType(AstBuilder.java:125)
        //     at cuchaz.enigma.source.procyon.ProcyonDecompiler.getSource(ProcyonDecompiler.java:75)
        //     at cuchaz.enigma.EnigmaProject$JarExport.decompileClass(EnigmaProject.java:270)
        //     at cuchaz.enigma.EnigmaProject$JarExport.lambda$decompileStream$1(EnigmaProject.java:246)
        //     at java.base/java.util.stream.ReferencePipeline$3$1.accept(ReferencePipeline.java:195)
        //     at java.base/java.util.ArrayList$ArrayListSpliterator.forEachRemaining(ArrayList.java:1624)
        //     at java.base/java.util.stream.AbstractPipeline.copyInto(AbstractPipeline.java:484)
        //     at java.base/java.util.stream.ForEachOps$ForEachTask.compute(ForEachOps.java:290)
        //     at java.base/java.util.concurrent.CountedCompleter.exec(CountedCompleter.java:746)
        //     at java.base/java.util.concurrent.ForkJoinTask.doExec(ForkJoinTask.java:290)
        //     at java.base/java.util.concurrent.ForkJoinPool$WorkQueue.topLevelExec(ForkJoinPool.java:1016)
        //     at java.base/java.util.concurrent.ForkJoinPool.scan(ForkJoinPool.java:1665)
        //     at java.base/java.util.concurrent.ForkJoinPool.runWorker(ForkJoinPool.java:1598)
        //     at java.base/java.util.concurrent.ForkJoinWorkerThread.run(ForkJoinWorkerThread.java:177)
        // 
        throw new IllegalStateException("An error occurred while decompiling this method.");
    }
    
    public static void ensureFromTo(final long[][] a, final long from, final long to) {
        BigArrays.ensureFromTo(length(a), from, to);
    }
    
    public static void ensureOffsetLength(final long[][] a, final long offset, final long length) {
        BigArrays.ensureOffsetLength(length(a), offset, length);
    }
    
    private static void vecSwap(final long[][] x, long a, long b, final long n) {
        for (int i = 0; i < n; ++i, ++a, ++b) {
            swap(x, a, b);
        }
    }
    
    private static long med3(final long[][] x, final long a, final long b, final long c, final LongComparator comp) {
        final int ab = comp.compare(get(x, a), get(x, b));
        final int ac = comp.compare(get(x, a), get(x, c));
        final int bc = comp.compare(get(x, b), get(x, c));
        return (ab < 0) ? ((bc < 0) ? b : ((ac < 0) ? c : a)) : ((bc > 0) ? b : ((ac > 0) ? c : a));
    }
    
    private static void selectionSort(final long[][] a, final long from, final long to, final LongComparator comp) {
        for (long i = from; i < to - 1L; ++i) {
            long m = i;
            for (long j = i + 1L; j < to; ++j) {
                if (comp.compare(get(a, j), get(a, m)) < 0) {
                    m = j;
                }
            }
            if (m != i) {
                swap(a, i, m);
            }
        }
    }
    
    public static void quickSort(final long[][] x, final long from, final long to, final LongComparator comp) {
        final long len = to - from;
        if (len < 7L) {
            selectionSort(x, from, to, comp);
            return;
        }
        long m = from + len / 2L;
        if (len > 7L) {
            long l = from;
            long n = to - 1L;
            if (len > 40L) {
                final long s = len / 8L;
                l = med3(x, l, l + s, l + 2L * s, comp);
                m = med3(x, m - s, m, m + s, comp);
                n = med3(x, n - 2L * s, n - s, n, comp);
            }
            m = med3(x, l, m, n, comp);
        }
        final long v = get(x, m);
        long b;
        long a = b = from;
        long d;
        long c = d = to - 1L;
        while (true) {
            int comparison;
            if (b <= c && (comparison = comp.compare(get(x, b), v)) <= 0) {
                if (comparison == 0) {
                    swap(x, a++, b);
                }
                ++b;
            }
            else {
                while (c >= b && (comparison = comp.compare(get(x, c), v)) >= 0) {
                    if (comparison == 0) {
                        swap(x, c, d--);
                    }
                    --c;
                }
                if (b > c) {
                    break;
                }
                swap(x, b++, c--);
            }
        }
        final long n2 = to;
        long s2 = Math.min(a - from, b - a);
        vecSwap(x, from, b - s2, s2);
        s2 = Math.min(d - c, n2 - d - 1L);
        vecSwap(x, b, n2 - s2, s2);
        if ((s2 = b - a) > 1L) {
            quickSort(x, from, from + s2, comp);
        }
        if ((s2 = d - c) > 1L) {
            quickSort(x, n2 - s2, n2, comp);
        }
    }
    
    private static long med3(final long[][] x, final long a, final long b, final long c) {
        final int ab = Long.compare(get(x, a), get(x, b));
        final int ac = Long.compare(get(x, a), get(x, c));
        final int bc = Long.compare(get(x, b), get(x, c));
        return (ab < 0) ? ((bc < 0) ? b : ((ac < 0) ? c : a)) : ((bc > 0) ? b : ((ac > 0) ? c : a));
    }
    
    private static void selectionSort(final long[][] a, final long from, final long to) {
        for (long i = from; i < to - 1L; ++i) {
            long m = i;
            for (long j = i + 1L; j < to; ++j) {
                if (get(a, j) < get(a, m)) {
                    m = j;
                }
            }
            if (m != i) {
                swap(a, i, m);
            }
        }
    }
    
    public static void quickSort(final long[][] x, final LongComparator comp) {
        quickSort(x, 0L, length(x), comp);
    }
    
    public static void quickSort(final long[][] x, final long from, final long to) {
        final long len = to - from;
        if (len < 7L) {
            selectionSort(x, from, to);
            return;
        }
        long m = from + len / 2L;
        if (len > 7L) {
            long l = from;
            long n = to - 1L;
            if (len > 40L) {
                final long s = len / 8L;
                l = med3(x, l, l + s, l + 2L * s);
                m = med3(x, m - s, m, m + s);
                n = med3(x, n - 2L * s, n - s, n);
            }
            m = med3(x, l, m, n);
        }
        final long v = get(x, m);
        long b;
        long a = b = from;
        long d;
        long c = d = to - 1L;
        while (true) {
            int comparison;
            if (b <= c && (comparison = Long.compare(get(x, b), v)) <= 0) {
                if (comparison == 0) {
                    swap(x, a++, b);
                }
                ++b;
            }
            else {
                while (c >= b && (comparison = Long.compare(get(x, c), v)) >= 0) {
                    if (comparison == 0) {
                        swap(x, c, d--);
                    }
                    --c;
                }
                if (b > c) {
                    break;
                }
                swap(x, b++, c--);
            }
        }
        final long n2 = to;
        long s2 = Math.min(a - from, b - a);
        vecSwap(x, from, b - s2, s2);
        s2 = Math.min(d - c, n2 - d - 1L);
        vecSwap(x, b, n2 - s2, s2);
        if ((s2 = b - a) > 1L) {
            quickSort(x, from, from + s2);
        }
        if ((s2 = d - c) > 1L) {
            quickSort(x, n2 - s2, n2);
        }
    }
    
    public static void quickSort(final long[][] x) {
        quickSort(x, 0L, length(x));
    }
    
    public static long binarySearch(final long[][] a, long from, long to, final long key) {
        --to;
        while (from <= to) {
            final long mid = from + to >>> 1;
            final long midVal = get(a, mid);
            if (midVal < key) {
                from = mid + 1L;
            }
            else {
                if (midVal <= key) {
                    return mid;
                }
                to = mid - 1L;
            }
        }
        return -(from + 1L);
    }
    
    public static long binarySearch(final long[][] a, final long key) {
        return binarySearch(a, 0L, length(a), key);
    }
    
    public static long binarySearch(final long[][] a, long from, long to, final long key, final LongComparator c) {
        --to;
        while (from <= to) {
            final long mid = from + to >>> 1;
            final long midVal = get(a, mid);
            final int cmp = c.compare(midVal, key);
            if (cmp < 0) {
                from = mid + 1L;
            }
            else {
                if (cmp <= 0) {
                    return mid;
                }
                to = mid - 1L;
            }
        }
        return -(from + 1L);
    }
    
    public static long binarySearch(final long[][] a, final long key, final LongComparator c) {
        return binarySearch(a, 0L, length(a), key, c);
    }
    
    public static void radixSort(final long[][] a) {
        radixSort(a, 0L, length(a));
    }
    
    public static void radixSort(final long[][] a, final long from, final long to) {
        final int maxLevel = 7;
        final int stackSize = 1786;
        final long[] offsetStack = new long[1786];
        int offsetPos = 0;
        final long[] lengthStack = new long[1786];
        int lengthPos = 0;
        final int[] levelStack = new int[1786];
        int levelPos = 0;
        offsetStack[offsetPos++] = from;
        lengthStack[lengthPos++] = to - from;
        levelStack[levelPos++] = 0;
        final long[] count = new long[256];
        final long[] pos = new long[256];
        final byte[][] digit = ByteBigArrays.newBigArray(to - from);
        while (offsetPos > 0) {
            final long first = offsetStack[--offsetPos];
            final long length = lengthStack[--lengthPos];
            final int level = levelStack[--levelPos];
            final int signMask = (level % 8 == 0) ? 128 : 0;
            if (length < 40L) {
                selectionSort(a, first, first + length);
            }
            else {
                final int shift = (7 - level % 8) * 8;
                long i = length;
                while (i-- != 0L) {
                    ByteBigArrays.set(digit, i, (byte)((get(a, first + i) >>> shift & 0xFFL) ^ (long)signMask));
                }
                i = length;
                while (i-- != 0L) {
                    final long[] array = count;
                    final int n = ByteBigArrays.get(digit, i) & 0xFF;
                    ++array[n];
                }
                int lastUsed = -1;
                long p = 0L;
                for (int j = 0; j < 256; ++j) {
                    if (count[j] != 0L) {
                        lastUsed = j;
                        if (level < 7 && count[j] > 1L) {
                            offsetStack[offsetPos++] = p + first;
                            lengthStack[lengthPos++] = count[j];
                            levelStack[levelPos++] = level + 1;
                        }
                    }
                    p = (pos[j] = p + count[j]);
                }
                final long end = length - count[lastUsed];
                count[lastUsed] = 0L;
                int c = -1;
                for (long k = 0L; k < end; k += count[c], count[c] = 0L) {
                    long t = get(a, k + first);
                    c = (ByteBigArrays.get(digit, k) & 0xFF);
                    while (true) {
                        final long[] array2 = pos;
                        final int n2 = c;
                        final long n3 = array2[n2] - 1L;
                        array2[n2] = n3;
                        final long d = n3;
                        if (n3 <= k) {
                            break;
                        }
                        final long z = t;
                        final int zz = c;
                        t = get(a, d + first);
                        c = (ByteBigArrays.get(digit, d) & 0xFF);
                        set(a, d + first, z);
                        ByteBigArrays.set(digit, d, (byte)zz);
                    }
                    set(a, k + first, t);
                }
            }
        }
    }
    
    private static void selectionSort(final long[][] a, final long[][] b, final long from, final long to) {
        for (long i = from; i < to - 1L; ++i) {
            long m = i;
            for (long j = i + 1L; j < to; ++j) {
                if (get(a, j) < get(a, m) || (get(a, j) == get(a, m) && get(b, j) < get(b, m))) {
                    m = j;
                }
            }
            if (m != i) {
                long t = get(a, i);
                set(a, i, get(a, m));
                set(a, m, t);
                t = get(b, i);
                set(b, i, get(b, m));
                set(b, m, t);
            }
        }
    }
    
    public static void radixSort(final long[][] a, final long[][] b) {
        radixSort(a, b, 0L, length(a));
    }
    
    public static void radixSort(final long[][] a, final long[][] b, final long from, final long to) {
        final int layers = 2;
        if (length(a) != length(b)) {
            throw new IllegalArgumentException("Array size mismatch.");
        }
        final int maxLevel = 15;
        final int stackSize = 3826;
        final long[] offsetStack = new long[3826];
        int offsetPos = 0;
        final long[] lengthStack = new long[3826];
        int lengthPos = 0;
        final int[] levelStack = new int[3826];
        int levelPos = 0;
        offsetStack[offsetPos++] = from;
        lengthStack[lengthPos++] = to - from;
        levelStack[levelPos++] = 0;
        final long[] count = new long[256];
        final long[] pos = new long[256];
        final byte[][] digit = ByteBigArrays.newBigArray(to - from);
        while (offsetPos > 0) {
            final long first = offsetStack[--offsetPos];
            final long length = lengthStack[--lengthPos];
            final int level = levelStack[--levelPos];
            final int signMask = (level % 8 == 0) ? 128 : 0;
            if (length < 40L) {
                selectionSort(a, b, first, first + length);
            }
            else {
                final long[][] k = (level < 8) ? a : b;
                final int shift = (7 - level % 8) * 8;
                long i = length;
                while (i-- != 0L) {
                    ByteBigArrays.set(digit, i, (byte)((get(k, first + i) >>> shift & 0xFFL) ^ (long)signMask));
                }
                i = length;
                while (i-- != 0L) {
                    final long[] array = count;
                    final int n = ByteBigArrays.get(digit, i) & 0xFF;
                    ++array[n];
                }
                int lastUsed = -1;
                long p = 0L;
                for (int j = 0; j < 256; ++j) {
                    if (count[j] != 0L) {
                        lastUsed = j;
                        if (level < 15 && count[j] > 1L) {
                            offsetStack[offsetPos++] = p + first;
                            lengthStack[lengthPos++] = count[j];
                            levelStack[levelPos++] = level + 1;
                        }
                    }
                    p = (pos[j] = p + count[j]);
                }
                final long end = length - count[lastUsed];
                count[lastUsed] = 0L;
                int c = -1;
                for (long l = 0L; l < end; l += count[c], count[c] = 0L) {
                    long t = get(a, l + first);
                    long u = get(b, l + first);
                    c = (ByteBigArrays.get(digit, l) & 0xFF);
                    while (true) {
                        final long[] array2 = pos;
                        final int n2 = c;
                        final long n3 = array2[n2] - 1L;
                        array2[n2] = n3;
                        final long d = n3;
                        if (n3 <= l) {
                            break;
                        }
                        long z = t;
                        final int zz = c;
                        t = get(a, d + first);
                        set(a, d + first, z);
                        z = u;
                        u = get(b, d + first);
                        set(b, d + first, z);
                        c = (ByteBigArrays.get(digit, d) & 0xFF);
                        ByteBigArrays.set(digit, d, (byte)zz);
                    }
                    set(a, l + first, t);
                    set(b, l + first, u);
                }
            }
        }
    }
    
    public static long[][] shuffle(final long[][] a, final long from, final long to, final Random random) {
        long i = to - from;
        while (i-- != 0L) {
            final long p = (random.nextLong() & Long.MAX_VALUE) % (i + 1L);
            final long t = get(a, from + i);
            set(a, from + i, get(a, from + p));
            set(a, from + p, t);
        }
        return a;
    }
    
    public static long[][] shuffle(final long[][] a, final Random random) {
        long i = length(a);
        while (i-- != 0L) {
            final long p = (random.nextLong() & Long.MAX_VALUE) % (i + 1L);
            final long t = get(a, i);
            set(a, i, get(a, p));
            set(a, p, t);
        }
        return a;
    }
    
    static {
        EMPTY_BIG_ARRAY = new long[0][];
        DEFAULT_EMPTY_BIG_ARRAY = new long[0][];
        HASH_STRATEGY = new BigArrayHashStrategy();
    }
    
    private static final class BigArrayHashStrategy implements Hash.Strategy<long[][]>, Serializable {
        private static final long serialVersionUID = -7046029254386353129L;
        
        public int hashCode(final long[][] o) {
            return Arrays.deepHashCode((Object[])o);
        }
        
        public boolean equals(final long[][] a, final long[][] b) {
            return LongBigArrays.equals(a, b);
        }
    }
}
