package it.unimi.dsi.fastutil.bytes;

import java.util.function.Consumer;
import it.unimi.dsi.fastutil.objects.ObjectIterator;
import java.util.Collection;
import java.util.Set;
import java.util.function.Function;
import java.util.function.BiFunction;
import java.util.function.IntFunction;
import java.util.Objects;
import it.unimi.dsi.fastutil.objects.ObjectCollection;
import it.unimi.dsi.fastutil.objects.ObjectSet;
import java.util.Map;

public interface Byte2ObjectMap<V> extends Byte2ObjectFunction<V>, Map<Byte, V> {
    int size();
    
    default void clear() {
        throw new UnsupportedOperationException();
    }
    
    void defaultReturnValue(final V object);
    
    V defaultReturnValue();
    
    ObjectSet<Entry<V>> byte2ObjectEntrySet();
    
    @Deprecated
    default ObjectSet<Map.Entry<Byte, V>> entrySet() {
        return (ObjectSet<Map.Entry<Byte, V>>)this.byte2ObjectEntrySet();
    }
    
    @Deprecated
    default V put(final Byte key, final V value) {
        return super.put(key, value);
    }
    
    @Deprecated
    default V get(final Object key) {
        return super.get(key);
    }
    
    @Deprecated
    default V remove(final Object key) {
        return super.remove(key);
    }
    
    ByteSet keySet();
    
    ObjectCollection<V> values();
    
    boolean containsKey(final byte byte1);
    
    @Deprecated
    default boolean containsKey(final Object key) {
        return super.containsKey(key);
    }
    
    default V getOrDefault(final byte key, final V defaultValue) {
        final V v;
        return ((v = this.get(key)) != this.defaultReturnValue() || this.containsKey(key)) ? v : defaultValue;
    }
    
    default V putIfAbsent(final byte key, final V value) {
        final V v = this.get(key);
        final V drv = this.defaultReturnValue();
        if (v != drv || this.containsKey(key)) {
            return v;
        }
        this.put(key, value);
        return drv;
    }
    
    default boolean remove(final byte key, final Object value) {
        final V curValue = this.get(key);
        if (!Objects.equals(curValue, value) || (curValue == this.defaultReturnValue() && !this.containsKey(key))) {
            return false;
        }
        this.remove(key);
        return true;
    }
    
    default boolean replace(final byte key, final V oldValue, final V newValue) {
        final V curValue = this.get(key);
        if (!Objects.equals(curValue, oldValue) || (curValue == this.defaultReturnValue() && !this.containsKey(key))) {
            return false;
        }
        this.put(key, newValue);
        return true;
    }
    
    default V replace(final byte key, final V value) {
        return this.containsKey(key) ? this.put(key, value) : this.defaultReturnValue();
    }
    
    default V computeIfAbsent(final byte key, final IntFunction<? extends V> mappingFunction) {
        Objects.requireNonNull(mappingFunction);
        final V v = this.get(key);
        if (v != this.defaultReturnValue() || this.containsKey(key)) {
            return v;
        }
        final V newValue = (V)mappingFunction.apply((int)key);
        this.put(key, newValue);
        return newValue;
    }
    
    default V computeIfAbsentPartial(final byte key, final Byte2ObjectFunction<? extends V> mappingFunction) {
        // 
        // This method could not be decompiled.
        // 
        // Original Bytecode:
        // 
        //     1: invokestatic    java/util/Objects.requireNonNull:(Ljava/lang/Object;)Ljava/lang/Object;
        //     4: pop            
        //     5: aload_0         /* this */
        //     6: iload_1         /* key */
        //     7: invokeinterface it/unimi/dsi/fastutil/bytes/Byte2ObjectMap.get:(B)Ljava/lang/Object;
        //    12: astore_3        /* v */
        //    13: aload_0         /* this */
        //    14: invokeinterface it/unimi/dsi/fastutil/bytes/Byte2ObjectMap.defaultReturnValue:()Ljava/lang/Object;
        //    19: astore          drv
        //    21: aload_3         /* v */
        //    22: aload           drv
        //    24: if_acmpne       37
        //    27: aload_0         /* this */
        //    28: iload_1         /* key */
        //    29: invokeinterface it/unimi/dsi/fastutil/bytes/Byte2ObjectMap.containsKey:(B)Z
        //    34: ifeq            39
        //    37: aload_3         /* v */
        //    38: areturn        
        //    39: aload_2         /* mappingFunction */
        //    40: iload_1         /* key */
        //    41: invokeinterface it/unimi/dsi/fastutil/bytes/Byte2ObjectFunction.containsKey:(B)Z
        //    46: ifne            52
        //    49: aload           drv
        //    51: areturn        
        //    52: aload_2         /* mappingFunction */
        //    53: iload_1         /* key */
        //    54: invokeinterface it/unimi/dsi/fastutil/bytes/Byte2ObjectFunction.get:(B)Ljava/lang/Object;
        //    59: astore          newValue
        //    61: aload_0         /* this */
        //    62: iload_1         /* key */
        //    63: aload           newValue
        //    65: invokeinterface it/unimi/dsi/fastutil/bytes/Byte2ObjectMap.put:(BLjava/lang/Object;)Ljava/lang/Object;
        //    70: pop            
        //    71: aload           newValue
        //    73: areturn        
        //    Signature:
        //  (BLit/unimi/dsi/fastutil/bytes/Byte2ObjectFunction<+TV;>;)TV;
        //    MethodParameters:
        //  Name             Flags  
        //  ---------------  -----
        //  key              
        //  mappingFunction  
        //    StackMapTable: 00 03 FD 00 25 07 00 05 07 00 05 01 0C
        // 
        // The error that occurred was:
        // 
        // java.lang.ArrayIndexOutOfBoundsException: Array index out of range: 1
        //     at java.base/java.util.Vector.get(Vector.java:749)
        //     at com.strobel.assembler.metadata.MetadataResolver.resolve(MetadataResolver.java:82)
        //     at com.strobel.assembler.metadata.CoreMetadataFactory$UnresolvedType.resolve(CoreMetadataFactory.java:616)
        //     at com.strobel.assembler.metadata.MetadataHelper.getGenericSubTypeMappings(MetadataHelper.java:764)
        //     at com.strobel.assembler.metadata.MetadataHelper.getGenericSubTypeMappings(MetadataHelper.java:805)
        //     at com.strobel.assembler.metadata.MetadataHelper.getGenericSubTypeMappings(MetadataHelper.java:805)
        //     at com.strobel.decompiler.ast.TypeAnalysis.inferCall(TypeAnalysis.java:2503)
        //     at com.strobel.decompiler.ast.TypeAnalysis.doInferTypeForExpression(TypeAnalysis.java:1029)
        //     at com.strobel.decompiler.ast.TypeAnalysis.inferTypeForExpression(TypeAnalysis.java:803)
        //     at com.strobel.decompiler.ast.TypeAnalysis.runInference(TypeAnalysis.java:672)
        //     at com.strobel.decompiler.ast.TypeAnalysis.runInference(TypeAnalysis.java:655)
        //     at com.strobel.decompiler.ast.TypeAnalysis.runInference(TypeAnalysis.java:365)
        //     at com.strobel.decompiler.ast.TypeAnalysis.run(TypeAnalysis.java:96)
        //     at com.strobel.decompiler.ast.AstOptimizer.optimize(AstOptimizer.java:109)
        //     at com.strobel.decompiler.ast.AstOptimizer.optimize(AstOptimizer.java:42)
        //     at com.strobel.decompiler.languages.java.ast.AstMethodBodyBuilder.createMethodBody(AstMethodBodyBuilder.java:214)
        //     at com.strobel.decompiler.languages.java.ast.AstMethodBodyBuilder.createMethodBody(AstMethodBodyBuilder.java:99)
        //     at com.strobel.decompiler.languages.java.ast.AstBuilder.createMethodBody(AstBuilder.java:782)
        //     at com.strobel.decompiler.languages.java.ast.AstBuilder.createMethod(AstBuilder.java:675)
        //     at com.strobel.decompiler.languages.java.ast.AstBuilder.addTypeMembers(AstBuilder.java:552)
        //     at com.strobel.decompiler.languages.java.ast.AstBuilder.createTypeCore(AstBuilder.java:519)
        //     at com.strobel.decompiler.languages.java.ast.AstBuilder.createTypeNoCache(AstBuilder.java:161)
        //     at com.strobel.decompiler.languages.java.ast.AstBuilder.createType(AstBuilder.java:150)
        //     at com.strobel.decompiler.languages.java.ast.AstBuilder.addType(AstBuilder.java:125)
        //     at cuchaz.enigma.source.procyon.ProcyonDecompiler.getSource(ProcyonDecompiler.java:75)
        //     at cuchaz.enigma.EnigmaProject$JarExport.decompileClass(EnigmaProject.java:270)
        //     at cuchaz.enigma.EnigmaProject$JarExport.lambda$decompileStream$1(EnigmaProject.java:246)
        //     at java.base/java.util.stream.ReferencePipeline$3$1.accept(ReferencePipeline.java:195)
        //     at java.base/java.util.ArrayList$ArrayListSpliterator.forEachRemaining(ArrayList.java:1624)
        //     at java.base/java.util.stream.AbstractPipeline.copyInto(AbstractPipeline.java:484)
        //     at java.base/java.util.stream.ForEachOps$ForEachTask.compute(ForEachOps.java:290)
        //     at java.base/java.util.concurrent.CountedCompleter.exec(CountedCompleter.java:746)
        //     at java.base/java.util.concurrent.ForkJoinTask.doExec(ForkJoinTask.java:290)
        //     at java.base/java.util.concurrent.ForkJoinPool$WorkQueue.helpCC(ForkJoinPool.java:1116)
        //     at java.base/java.util.concurrent.ForkJoinPool.externalHelpComplete(ForkJoinPool.java:1966)
        //     at java.base/java.util.concurrent.ForkJoinTask.tryExternalHelp(ForkJoinTask.java:378)
        //     at java.base/java.util.concurrent.ForkJoinTask.externalAwaitDone(ForkJoinTask.java:323)
        //     at java.base/java.util.concurrent.ForkJoinTask.doInvoke(ForkJoinTask.java:412)
        //     at java.base/java.util.concurrent.ForkJoinTask.invoke(ForkJoinTask.java:736)
        //     at java.base/java.util.stream.ForEachOps$ForEachOp.evaluateParallel(ForEachOps.java:159)
        //     at java.base/java.util.stream.ForEachOps$ForEachOp$OfRef.evaluateParallel(ForEachOps.java:173)
        //     at java.base/java.util.stream.AbstractPipeline.evaluate(AbstractPipeline.java:233)
        //     at java.base/java.util.stream.ReferencePipeline.forEach(ReferencePipeline.java:497)
        //     at cuchaz.enigma.gui.GuiController.lambda$exportSource$6(GuiController.java:216)
        //     at cuchaz.enigma.gui.dialog.ProgressDialog.lambda$runOffThread$0(ProgressDialog.java:78)
        //     at java.base/java.lang.Thread.run(Thread.java:832)
        // 
        throw new IllegalStateException("An error occurred while decompiling this method.");
    }
    
    default V computeIfPresent(final byte key, final BiFunction<? super Byte, ? super V, ? extends V> remappingFunction) {
        Objects.requireNonNull(remappingFunction);
        final V oldValue = this.get(key);
        final V drv = this.defaultReturnValue();
        if (oldValue == drv && !this.containsKey(key)) {
            return drv;
        }
        final V newValue = (V)remappingFunction.apply(key, oldValue);
        if (newValue == null) {
            this.remove(key);
            return drv;
        }
        this.put(key, newValue);
        return newValue;
    }
    
    default V compute(final byte key, final BiFunction<? super Byte, ? super V, ? extends V> remappingFunction) {
        Objects.requireNonNull(remappingFunction);
        final V oldValue = this.get(key);
        final V drv = this.defaultReturnValue();
        final boolean contained = oldValue != drv || this.containsKey(key);
        final V newValue = (V)remappingFunction.apply(key, (contained ? oldValue : null));
        if (newValue == null) {
            if (contained) {
                this.remove(key);
            }
            return drv;
        }
        this.put(key, newValue);
        return newValue;
    }
    
    default V merge(final byte key, final V value, final BiFunction<? super V, ? super V, ? extends V> remappingFunction) {
        Objects.requireNonNull(remappingFunction);
        Objects.requireNonNull(value);
        final V oldValue = this.get(key);
        final V drv = this.defaultReturnValue();
        V newValue;
        if (oldValue != drv || this.containsKey(key)) {
            final V mergedValue = (V)remappingFunction.apply(oldValue, value);
            if (mergedValue == null) {
                this.remove(key);
                return drv;
            }
            newValue = mergedValue;
        }
        else {
            newValue = value;
        }
        this.put(key, newValue);
        return newValue;
    }
    
    @Deprecated
    default V getOrDefault(final Object key, final V defaultValue) {
        return (V)super.getOrDefault(key, defaultValue);
    }
    
    @Deprecated
    default V putIfAbsent(final Byte key, final V value) {
        return (V)super.putIfAbsent(key, value);
    }
    
    @Deprecated
    default boolean remove(final Object key, final Object value) {
        return super.remove(key, value);
    }
    
    @Deprecated
    default boolean replace(final Byte key, final V oldValue, final V newValue) {
        return super.replace(key, oldValue, newValue);
    }
    
    @Deprecated
    default V replace(final Byte key, final V value) {
        return (V)super.replace(key, value);
    }
    
    @Deprecated
    default V computeIfAbsent(final Byte key, final java.util.function.Function<? super Byte, ? extends V> mappingFunction) {
        return (V)super.computeIfAbsent(key, (java.util.function.Function)mappingFunction);
    }
    
    @Deprecated
    default V computeIfPresent(final Byte key, final BiFunction<? super Byte, ? super V, ? extends V> remappingFunction) {
        return (V)super.computeIfPresent(key, (BiFunction)remappingFunction);
    }
    
    @Deprecated
    default V compute(final Byte key, final BiFunction<? super Byte, ? super V, ? extends V> remappingFunction) {
        return (V)super.compute(key, (BiFunction)remappingFunction);
    }
    
    @Deprecated
    default V merge(final Byte key, final V value, final BiFunction<? super V, ? super V, ? extends V> remappingFunction) {
        return (V)super.merge(key, value, (BiFunction)remappingFunction);
    }
    
    public interface FastEntrySet<V> extends ObjectSet<Entry<V>> {
        ObjectIterator<Entry<V>> fastIterator();
        
        default void fastForEach(final Consumer<? super Entry<V>> consumer) {
            this.forEach((Consumer)consumer);
        }
    }
    
    public interface Entry<V> extends Map.Entry<Byte, V> {
        byte getByteKey();
        
        @Deprecated
        default Byte getKey() {
            return this.getByteKey();
        }
    }
}
