package it.unimi.dsi.fastutil.doubles;

import java.util.function.DoubleConsumer;
import it.unimi.dsi.fastutil.objects.AbstractObjectSet;
import java.util.NoSuchElementException;
import java.util.Set;
import java.util.Collection;
import it.unimi.dsi.fastutil.objects.ObjectSet;
import java.io.ObjectInputStream;
import java.io.IOException;
import java.io.ObjectOutputStream;
import java.util.Iterator;
import java.util.function.Consumer;
import it.unimi.dsi.fastutil.objects.ObjectIterator;
import it.unimi.dsi.fastutil.objects.AbstractReferenceCollection;
import java.util.Arrays;
import java.util.function.BiFunction;
import java.util.Objects;
import java.util.function.DoubleFunction;
import java.util.Map;
import it.unimi.dsi.fastutil.HashCommon;
import it.unimi.dsi.fastutil.objects.ReferenceCollection;
import it.unimi.dsi.fastutil.Hash;
import java.io.Serializable;

public class Double2ReferenceOpenHashMap<V> extends AbstractDouble2ReferenceMap<V> implements Serializable, Cloneable, Hash {
    private static final long serialVersionUID = 0L;
    private static final boolean ASSERTS = false;
    protected transient double[] key;
    protected transient V[] value;
    protected transient int mask;
    protected transient boolean containsNullKey;
    protected transient int n;
    protected transient int maxFill;
    protected final transient int minN;
    protected int size;
    protected final float f;
    protected transient Double2ReferenceMap.FastEntrySet<V> entries;
    protected transient DoubleSet keys;
    protected transient ReferenceCollection<V> values;
    
    public Double2ReferenceOpenHashMap(final int expected, final float f) {
        if (f <= 0.0f || f > 1.0f) {
            throw new IllegalArgumentException("Load factor must be greater than 0 and smaller than or equal to 1");
        }
        if (expected < 0) {
            throw new IllegalArgumentException("The expected number of elements must be nonnegative");
        }
        this.f = f;
        final int arraySize = HashCommon.arraySize(expected, f);
        this.n = arraySize;
        this.minN = arraySize;
        this.mask = this.n - 1;
        this.maxFill = HashCommon.maxFill(this.n, f);
        this.key = new double[this.n + 1];
        this.value = (V[])new Object[this.n + 1];
    }
    
    public Double2ReferenceOpenHashMap(final int expected) {
        this(expected, 0.75f);
    }
    
    public Double2ReferenceOpenHashMap() {
        this(16, 0.75f);
    }
    
    public Double2ReferenceOpenHashMap(final Map<? extends Double, ? extends V> m, final float f) {
        this(m.size(), f);
        this.putAll(m);
    }
    
    public Double2ReferenceOpenHashMap(final Map<? extends Double, ? extends V> m) {
        this(m, 0.75f);
    }
    
    public Double2ReferenceOpenHashMap(final Double2ReferenceMap<V> m, final float f) {
        this(m.size(), f);
        this.putAll(m);
    }
    
    public Double2ReferenceOpenHashMap(final Double2ReferenceMap<V> m) {
        this(m, 0.75f);
    }
    
    public Double2ReferenceOpenHashMap(final double[] k, final V[] v, final float f) {
        this(k.length, f);
        if (k.length != v.length) {
            throw new IllegalArgumentException(new StringBuilder().append("The key array and the value array have different lengths (").append(k.length).append(" and ").append(v.length).append(")").toString());
        }
        for (int i = 0; i < k.length; ++i) {
            this.put(k[i], v[i]);
        }
    }
    
    public Double2ReferenceOpenHashMap(final double[] k, final V[] v) {
        this(k, v, 0.75f);
    }
    
    private int realSize() {
        return this.containsNullKey ? (this.size - 1) : this.size;
    }
    
    private void ensureCapacity(final int capacity) {
        final int needed = HashCommon.arraySize(capacity, this.f);
        if (needed > this.n) {
            this.rehash(needed);
        }
    }
    
    private void tryCapacity(final long capacity) {
        final int needed = (int)Math.min(1073741824L, Math.max(2L, HashCommon.nextPowerOfTwo((long)Math.ceil((double)(capacity / this.f)))));
        if (needed > this.n) {
            this.rehash(needed);
        }
    }
    
    private V removeEntry(final int pos) {
        final V oldValue = this.value[pos];
        this.value[pos] = null;
        --this.size;
        this.shiftKeys(pos);
        if (this.n > this.minN && this.size < this.maxFill / 4 && this.n > 16) {
            this.rehash(this.n / 2);
        }
        return oldValue;
    }
    
    private V removeNullEntry() {
        this.containsNullKey = false;
        final V oldValue = this.value[this.n];
        this.value[this.n] = null;
        --this.size;
        if (this.n > this.minN && this.size < this.maxFill / 4 && this.n > 16) {
            this.rehash(this.n / 2);
        }
        return oldValue;
    }
    
    @Override
    public void putAll(final Map<? extends Double, ? extends V> m) {
        if (this.f <= 0.5) {
            this.ensureCapacity(m.size());
        }
        else {
            this.tryCapacity(this.size() + m.size());
        }
        super.putAll(m);
    }
    
    private int find(final double k) {
        if (Double.doubleToLongBits(k) == 0L) {
            return this.containsNullKey ? this.n : (-(this.n + 1));
        }
        final double[] key = this.key;
        int pos;
        double curr;
        if (Double.doubleToLongBits(curr = key[pos = ((int)HashCommon.mix(Double.doubleToRawLongBits(k)) & this.mask)]) == 0L) {
            return -(pos + 1);
        }
        if (Double.doubleToLongBits(k) == Double.doubleToLongBits(curr)) {
            return pos;
        }
        while (Double.doubleToLongBits(curr = key[pos = (pos + 1 & this.mask)]) != 0L) {
            if (Double.doubleToLongBits(k) == Double.doubleToLongBits(curr)) {
                return pos;
            }
        }
        return -(pos + 1);
    }
    
    private void insert(final int pos, final double k, final V v) {
        if (pos == this.n) {
            this.containsNullKey = true;
        }
        this.key[pos] = k;
        this.value[pos] = v;
        if (this.size++ >= this.maxFill) {
            this.rehash(HashCommon.arraySize(this.size + 1, this.f));
        }
    }
    
    public V put(final double k, final V v) {
        final int pos = this.find(k);
        if (pos < 0) {
            this.insert(-pos - 1, k, v);
            return this.defRetValue;
        }
        final V oldValue = this.value[pos];
        this.value[pos] = v;
        return oldValue;
    }
    
    protected final void shiftKeys(int pos) {
        final double[] key = this.key;
        int last = 0;
    Label_0006:
        while (true) {
            pos = ((last = pos) + 1 & this.mask);
            double curr;
            while (Double.doubleToLongBits(curr = key[pos]) != 0L) {
                final int slot = (int)HashCommon.mix(Double.doubleToRawLongBits(curr)) & this.mask;
                Label_0103: {
                    if (last <= pos) {
                        if (last >= slot) {
                            break Label_0103;
                        }
                        if (slot > pos) {
                            break Label_0103;
                        }
                    }
                    else if (last >= slot && slot > pos) {
                        break Label_0103;
                    }
                    pos = (pos + 1 & this.mask);
                    continue;
                }
                key[last] = curr;
                this.value[last] = this.value[pos];
                continue Label_0006;
            }
            break;
        }
        key[last] = 0.0;
        this.value[last] = null;
    }
    
    public V remove(final double k) {
        if (Double.doubleToLongBits(k) == 0L) {
            if (this.containsNullKey) {
                return this.removeNullEntry();
            }
            return this.defRetValue;
        }
        else {
            final double[] key = this.key;
            int pos;
            double curr;
            if (Double.doubleToLongBits(curr = key[pos = ((int)HashCommon.mix(Double.doubleToRawLongBits(k)) & this.mask)]) == 0L) {
                return this.defRetValue;
            }
            if (Double.doubleToLongBits(k) == Double.doubleToLongBits(curr)) {
                return this.removeEntry(pos);
            }
            while (Double.doubleToLongBits(curr = key[pos = (pos + 1 & this.mask)]) != 0L) {
                if (Double.doubleToLongBits(k) == Double.doubleToLongBits(curr)) {
                    return this.removeEntry(pos);
                }
            }
            return this.defRetValue;
        }
    }
    
    public V get(final double k) {
        if (Double.doubleToLongBits(k) == 0L) {
            return this.containsNullKey ? this.value[this.n] : this.defRetValue;
        }
        final double[] key = this.key;
        int pos;
        double curr;
        if (Double.doubleToLongBits(curr = key[pos = ((int)HashCommon.mix(Double.doubleToRawLongBits(k)) & this.mask)]) == 0L) {
            return this.defRetValue;
        }
        if (Double.doubleToLongBits(k) == Double.doubleToLongBits(curr)) {
            return this.value[pos];
        }
        while (Double.doubleToLongBits(curr = key[pos = (pos + 1 & this.mask)]) != 0L) {
            if (Double.doubleToLongBits(k) == Double.doubleToLongBits(curr)) {
                return this.value[pos];
            }
        }
        return this.defRetValue;
    }
    
    @Override
    public boolean containsKey(final double k) {
        // 
        // This method could not be decompiled.
        // 
        // Original Bytecode:
        // 
        //     1: invokestatic    java/lang/Double.doubleToLongBits:(D)J
        //     4: lconst_0       
        //     5: lcmp           
        //     6: ifne            14
        //     9: aload_0         /* this */
        //    10: getfield        it/unimi/dsi/fastutil/doubles/Double2ReferenceOpenHashMap.containsNullKey:Z
        //    13: ireturn        
        //    14: aload_0         /* this */
        //    15: getfield        it/unimi/dsi/fastutil/doubles/Double2ReferenceOpenHashMap.key:[D
        //    18: astore          key
        //    20: aload           key
        //    22: dload_1         /* k */
        //    23: invokestatic    java/lang/Double.doubleToRawLongBits:(D)J
        //    26: invokestatic    it/unimi/dsi/fastutil/HashCommon.mix:(J)J
        //    29: l2i            
        //    30: aload_0         /* this */
        //    31: getfield        it/unimi/dsi/fastutil/doubles/Double2ReferenceOpenHashMap.mask:I
        //    34: iand           
        //    35: dup            
        //    36: istore          pos
        //    38: daload         
        //    39: dup2           
        //    40: dstore_3        /* curr */
        //    41: invokestatic    java/lang/Double.doubleToLongBits:(D)J
        //    44: lconst_0       
        //    45: lcmp           
        //    46: ifne            51
        //    49: iconst_0       
        //    50: ireturn        
        //    51: dload_1         /* k */
        //    52: invokestatic    java/lang/Double.doubleToLongBits:(D)J
        //    55: dload_3         /* curr */
        //    56: invokestatic    java/lang/Double.doubleToLongBits:(D)J
        //    59: lcmp           
        //    60: ifne            65
        //    63: iconst_1       
        //    64: ireturn        
        //    65: aload           key
        //    67: iload           pos
        //    69: iconst_1       
        //    70: iadd           
        //    71: aload_0         /* this */
        //    72: getfield        it/unimi/dsi/fastutil/doubles/Double2ReferenceOpenHashMap.mask:I
        //    75: iand           
        //    76: dup            
        //    77: istore          pos
        //    79: daload         
        //    80: dup2           
        //    81: dstore_3        /* curr */
        //    82: invokestatic    java/lang/Double.doubleToLongBits:(D)J
        //    85: lconst_0       
        //    86: lcmp           
        //    87: ifne            92
        //    90: iconst_0       
        //    91: ireturn        
        //    92: dload_1         /* k */
        //    93: invokestatic    java/lang/Double.doubleToLongBits:(D)J
        //    96: dload_3         /* curr */
        //    97: invokestatic    java/lang/Double.doubleToLongBits:(D)J
        //   100: lcmp           
        //   101: ifne            65
        //   104: iconst_1       
        //   105: ireturn        
        //    MethodParameters:
        //  Name  Flags  
        //  ----  -----
        //  k     
        //    StackMapTable: 00 04 0E FE 00 24 03 07 00 A9 01 0D 1A
        // 
        // The error that occurred was:
        // 
        // java.lang.ArrayIndexOutOfBoundsException: Array index out of range: 37
        //     at java.base/java.util.Vector.get(Vector.java:749)
        //     at com.strobel.assembler.metadata.MetadataResolver.resolve(MetadataResolver.java:82)
        //     at com.strobel.assembler.metadata.CoreMetadataFactory$UnresolvedType.resolve(CoreMetadataFactory.java:616)
        //     at com.strobel.assembler.metadata.MetadataResolver.resolve(MetadataResolver.java:128)
        //     at com.strobel.assembler.metadata.CoreMetadataFactory$UnresolvedType.resolve(CoreMetadataFactory.java:626)
        //     at com.strobel.assembler.metadata.MethodReference.resolve(MethodReference.java:177)
        //     at com.strobel.decompiler.ast.TypeAnalysis.inferCall(TypeAnalysis.java:2438)
        //     at com.strobel.decompiler.ast.TypeAnalysis.doInferTypeForExpression(TypeAnalysis.java:1029)
        //     at com.strobel.decompiler.ast.TypeAnalysis.inferTypeForExpression(TypeAnalysis.java:803)
        //     at com.strobel.decompiler.ast.TypeAnalysis.runInference(TypeAnalysis.java:672)
        //     at com.strobel.decompiler.ast.TypeAnalysis.runInference(TypeAnalysis.java:655)
        //     at com.strobel.decompiler.ast.TypeAnalysis.inferBinaryExpression(TypeAnalysis.java:2104)
        //     at com.strobel.decompiler.ast.TypeAnalysis.doInferTypeForExpression(TypeAnalysis.java:1543)
        //     at com.strobel.decompiler.ast.TypeAnalysis.inferTypeForExpression(TypeAnalysis.java:803)
        //     at com.strobel.decompiler.ast.TypeAnalysis.runInference(TypeAnalysis.java:672)
        //     at com.strobel.decompiler.ast.TypeAnalysis.runInference(TypeAnalysis.java:655)
        //     at com.strobel.decompiler.ast.TypeAnalysis.inferBinaryExpression(TypeAnalysis.java:2104)
        //     at com.strobel.decompiler.ast.TypeAnalysis.doInferTypeForExpression(TypeAnalysis.java:1531)
        //     at com.strobel.decompiler.ast.TypeAnalysis.inferTypeForExpression(TypeAnalysis.java:803)
        //     at com.strobel.decompiler.ast.TypeAnalysis.inferTypeForExpression(TypeAnalysis.java:778)
        //     at com.strobel.decompiler.ast.TypeAnalysis.doInferTypeForExpression(TypeAnalysis.java:1551)
        //     at com.strobel.decompiler.ast.TypeAnalysis.inferTypeForExpression(TypeAnalysis.java:803)
        //     at com.strobel.decompiler.ast.TypeAnalysis.runInference(TypeAnalysis.java:672)
        //     at com.strobel.decompiler.ast.TypeAnalysis.inferTypesForVariables(TypeAnalysis.java:586)
        //     at com.strobel.decompiler.ast.TypeAnalysis.runInference(TypeAnalysis.java:397)
        //     at com.strobel.decompiler.ast.TypeAnalysis.run(TypeAnalysis.java:96)
        //     at com.strobel.decompiler.ast.AstOptimizer.optimize(AstOptimizer.java:109)
        //     at com.strobel.decompiler.ast.AstOptimizer.optimize(AstOptimizer.java:42)
        //     at com.strobel.decompiler.languages.java.ast.AstMethodBodyBuilder.createMethodBody(AstMethodBodyBuilder.java:214)
        //     at com.strobel.decompiler.languages.java.ast.AstMethodBodyBuilder.createMethodBody(AstMethodBodyBuilder.java:99)
        //     at com.strobel.decompiler.languages.java.ast.AstBuilder.createMethodBody(AstBuilder.java:782)
        //     at com.strobel.decompiler.languages.java.ast.AstBuilder.createMethod(AstBuilder.java:675)
        //     at com.strobel.decompiler.languages.java.ast.AstBuilder.addTypeMembers(AstBuilder.java:552)
        //     at com.strobel.decompiler.languages.java.ast.AstBuilder.createTypeCore(AstBuilder.java:519)
        //     at com.strobel.decompiler.languages.java.ast.AstBuilder.createTypeNoCache(AstBuilder.java:161)
        //     at com.strobel.decompiler.languages.java.ast.AstBuilder.createType(AstBuilder.java:150)
        //     at com.strobel.decompiler.languages.java.ast.AstBuilder.addType(AstBuilder.java:125)
        //     at cuchaz.enigma.source.procyon.ProcyonDecompiler.getSource(ProcyonDecompiler.java:75)
        //     at cuchaz.enigma.EnigmaProject$JarExport.decompileClass(EnigmaProject.java:270)
        //     at cuchaz.enigma.EnigmaProject$JarExport.lambda$decompileStream$1(EnigmaProject.java:246)
        //     at java.base/java.util.stream.ReferencePipeline$3$1.accept(ReferencePipeline.java:195)
        //     at java.base/java.util.ArrayList$ArrayListSpliterator.forEachRemaining(ArrayList.java:1624)
        //     at java.base/java.util.stream.AbstractPipeline.copyInto(AbstractPipeline.java:484)
        //     at java.base/java.util.stream.ForEachOps$ForEachTask.compute(ForEachOps.java:290)
        //     at java.base/java.util.concurrent.CountedCompleter.exec(CountedCompleter.java:746)
        //     at java.base/java.util.concurrent.ForkJoinTask.doExec(ForkJoinTask.java:290)
        //     at java.base/java.util.concurrent.ForkJoinPool$WorkQueue.topLevelExec(ForkJoinPool.java:1016)
        //     at java.base/java.util.concurrent.ForkJoinPool.scan(ForkJoinPool.java:1665)
        //     at java.base/java.util.concurrent.ForkJoinPool.runWorker(ForkJoinPool.java:1598)
        //     at java.base/java.util.concurrent.ForkJoinWorkerThread.run(ForkJoinWorkerThread.java:177)
        // 
        throw new IllegalStateException("An error occurred while decompiling this method.");
    }
    
    @Override
    public boolean containsValue(final Object v) {
        final V[] value = this.value;
        final double[] key = this.key;
        if (this.containsNullKey && value[this.n] == v) {
            return true;
        }
        int i = this.n;
        while (i-- != 0) {
            if (Double.doubleToLongBits(key[i]) != 0L && value[i] == v) {
                return true;
            }
        }
        return false;
    }
    
    public V getOrDefault(final double k, final V defaultValue) {
        if (Double.doubleToLongBits(k) == 0L) {
            return this.containsNullKey ? this.value[this.n] : defaultValue;
        }
        final double[] key = this.key;
        int pos;
        double curr;
        if (Double.doubleToLongBits(curr = key[pos = ((int)HashCommon.mix(Double.doubleToRawLongBits(k)) & this.mask)]) == 0L) {
            return defaultValue;
        }
        if (Double.doubleToLongBits(k) == Double.doubleToLongBits(curr)) {
            return this.value[pos];
        }
        while (Double.doubleToLongBits(curr = key[pos = (pos + 1 & this.mask)]) != 0L) {
            if (Double.doubleToLongBits(k) == Double.doubleToLongBits(curr)) {
                return this.value[pos];
            }
        }
        return defaultValue;
    }
    
    public V putIfAbsent(final double k, final V v) {
        final int pos = this.find(k);
        if (pos >= 0) {
            return this.value[pos];
        }
        this.insert(-pos - 1, k, v);
        return this.defRetValue;
    }
    
    public boolean remove(final double k, final Object v) {
        if (Double.doubleToLongBits(k) == 0L) {
            if (this.containsNullKey && v == this.value[this.n]) {
                this.removeNullEntry();
                return true;
            }
            return false;
        }
        else {
            final double[] key = this.key;
            int pos;
            double curr;
            if (Double.doubleToLongBits(curr = key[pos = ((int)HashCommon.mix(Double.doubleToRawLongBits(k)) & this.mask)]) == 0L) {
                return false;
            }
            if (Double.doubleToLongBits(k) == Double.doubleToLongBits(curr) && v == this.value[pos]) {
                this.removeEntry(pos);
                return true;
            }
            while (Double.doubleToLongBits(curr = key[pos = (pos + 1 & this.mask)]) != 0L) {
                if (Double.doubleToLongBits(k) == Double.doubleToLongBits(curr) && v == this.value[pos]) {
                    this.removeEntry(pos);
                    return true;
                }
            }
            return false;
        }
    }
    
    public boolean replace(final double k, final V oldValue, final V v) {
        final int pos = this.find(k);
        if (pos < 0 || oldValue != this.value[pos]) {
            return false;
        }
        this.value[pos] = v;
        return true;
    }
    
    public V replace(final double k, final V v) {
        final int pos = this.find(k);
        if (pos < 0) {
            return this.defRetValue;
        }
        final V oldValue = this.value[pos];
        this.value[pos] = v;
        return oldValue;
    }
    
    public V computeIfAbsent(final double k, final DoubleFunction<? extends V> mappingFunction) {
        Objects.requireNonNull(mappingFunction);
        final int pos = this.find(k);
        if (pos >= 0) {
            return this.value[pos];
        }
        final V newValue = (V)mappingFunction.apply(k);
        this.insert(-pos - 1, k, newValue);
        return newValue;
    }
    
    public V computeIfPresent(final double k, final BiFunction<? super Double, ? super V, ? extends V> remappingFunction) {
        Objects.requireNonNull(remappingFunction);
        final int pos = this.find(k);
        if (pos < 0) {
            return this.defRetValue;
        }
        final V newValue = (V)remappingFunction.apply(k, this.value[pos]);
        if (newValue == null) {
            if (Double.doubleToLongBits(k) == 0L) {
                this.removeNullEntry();
            }
            else {
                this.removeEntry(pos);
            }
            return this.defRetValue;
        }
        return this.value[pos] = newValue;
    }
    
    public V compute(final double k, final BiFunction<? super Double, ? super V, ? extends V> remappingFunction) {
        Objects.requireNonNull(remappingFunction);
        final int pos = this.find(k);
        final V newValue = (V)remappingFunction.apply(k, ((pos >= 0) ? this.value[pos] : null));
        if (newValue == null) {
            if (pos >= 0) {
                if (Double.doubleToLongBits(k) == 0L) {
                    this.removeNullEntry();
                }
                else {
                    this.removeEntry(pos);
                }
            }
            return this.defRetValue;
        }
        final V newVal = newValue;
        if (pos < 0) {
            this.insert(-pos - 1, k, newVal);
            return newVal;
        }
        return this.value[pos] = newVal;
    }
    
    public V merge(final double k, final V v, final BiFunction<? super V, ? super V, ? extends V> remappingFunction) {
        Objects.requireNonNull(remappingFunction);
        final int pos = this.find(k);
        if (pos < 0 || this.value[pos] == null) {
            if (v == null) {
                return this.defRetValue;
            }
            this.insert(-pos - 1, k, v);
            return v;
        }
        else {
            final V newValue = (V)remappingFunction.apply(this.value[pos], v);
            if (newValue == null) {
                if (Double.doubleToLongBits(k) == 0L) {
                    this.removeNullEntry();
                }
                else {
                    this.removeEntry(pos);
                }
                return this.defRetValue;
            }
            return this.value[pos] = newValue;
        }
    }
    
    public void clear() {
        if (this.size == 0) {
            return;
        }
        this.size = 0;
        this.containsNullKey = false;
        Arrays.fill(this.key, 0.0);
        Arrays.fill((Object[])this.value, null);
    }
    
    public int size() {
        return this.size;
    }
    
    @Override
    public boolean isEmpty() {
        return this.size == 0;
    }
    
    public Double2ReferenceMap.FastEntrySet<V> double2ReferenceEntrySet() {
        if (this.entries == null) {
            this.entries = new MapEntrySet();
        }
        return this.entries;
    }
    
    @Override
    public DoubleSet keySet() {
        if (this.keys == null) {
            this.keys = new KeySet();
        }
        return this.keys;
    }
    
    @Override
    public ReferenceCollection<V> values() {
        if (this.values == null) {
            this.values = new AbstractReferenceCollection<V>() {
                @Override
                public ObjectIterator<V> iterator() {
                    return new ValueIterator();
                }
                
                public int size() {
                    return Double2ReferenceOpenHashMap.this.size;
                }
                
                public boolean contains(final Object v) {
                    return Double2ReferenceOpenHashMap.this.containsValue(v);
                }
                
                public void clear() {
                    Double2ReferenceOpenHashMap.this.clear();
                }
                
                public void forEach(final Consumer<? super V> consumer) {
                    if (Double2ReferenceOpenHashMap.this.containsNullKey) {
                        consumer.accept(Double2ReferenceOpenHashMap.this.value[Double2ReferenceOpenHashMap.this.n]);
                    }
                    int pos = Double2ReferenceOpenHashMap.this.n;
                    while (pos-- != 0) {
                        if (Double.doubleToLongBits(Double2ReferenceOpenHashMap.this.key[pos]) != 0L) {
                            consumer.accept(Double2ReferenceOpenHashMap.this.value[pos]);
                        }
                    }
                }
            };
        }
        return this.values;
    }
    
    public boolean trim() {
        final int l = HashCommon.arraySize(this.size, this.f);
        if (l >= this.n || this.size > HashCommon.maxFill(l, this.f)) {
            return true;
        }
        try {
            this.rehash(l);
        }
        catch (OutOfMemoryError cantDoIt) {
            return false;
        }
        return true;
    }
    
    public boolean trim(final int n) {
        final int l = HashCommon.nextPowerOfTwo((int)Math.ceil((double)(n / this.f)));
        if (l >= n || this.size > HashCommon.maxFill(l, this.f)) {
            return true;
        }
        try {
            this.rehash(l);
        }
        catch (OutOfMemoryError cantDoIt) {
            return false;
        }
        return true;
    }
    
    protected void rehash(final int newN) {
        final double[] key = this.key;
        final V[] value = this.value;
        final int mask = newN - 1;
        final double[] newKey = new double[newN + 1];
        final V[] newValue = (V[])new Object[newN + 1];
        int i = this.n;
        int j = this.realSize();
        while (j-- != 0) {
            while (Double.doubleToLongBits(key[--i]) == 0L) {}
            int pos;
            if (Double.doubleToLongBits(newKey[pos = ((int)HashCommon.mix(Double.doubleToRawLongBits(key[i])) & mask)]) != 0L) {
                while (Double.doubleToLongBits(newKey[pos = (pos + 1 & mask)]) != 0L) {}
            }
            newKey[pos] = key[i];
            newValue[pos] = value[i];
        }
        newValue[newN] = value[this.n];
        this.n = newN;
        this.mask = mask;
        this.maxFill = HashCommon.maxFill(this.n, this.f);
        this.key = newKey;
        this.value = newValue;
    }
    
    public Double2ReferenceOpenHashMap<V> clone() {
        Double2ReferenceOpenHashMap<V> c;
        try {
            c = (Double2ReferenceOpenHashMap)super.clone();
        }
        catch (CloneNotSupportedException cantHappen) {
            throw new InternalError();
        }
        c.keys = null;
        c.values = null;
        c.entries = null;
        c.containsNullKey = this.containsNullKey;
        c.key = this.key.clone();
        c.value = this.value.clone();
        return c;
    }
    
    @Override
    public int hashCode() {
        int h = 0;
        int j = this.realSize();
        int i = 0;
        int t = 0;
        while (j-- != 0) {
            while (Double.doubleToLongBits(this.key[i]) == 0L) {
                ++i;
            }
            t = HashCommon.double2int(this.key[i]);
            if (this != this.value[i]) {
                t ^= ((this.value[i] == null) ? 0 : System.identityHashCode(this.value[i]));
            }
            h += t;
            ++i;
        }
        if (this.containsNullKey) {
            h += ((this.value[this.n] == null) ? 0 : System.identityHashCode(this.value[this.n]));
        }
        return h;
    }
    
    private void writeObject(final ObjectOutputStream s) throws IOException {
        final double[] key = this.key;
        final V[] value = this.value;
        final MapIterator i = new MapIterator();
        s.defaultWriteObject();
        int j = this.size;
        while (j-- != 0) {
            final int e = i.nextEntry();
            s.writeDouble(key[e]);
            s.writeObject(value[e]);
        }
    }
    
    private void readObject(final ObjectInputStream s) throws IOException, ClassNotFoundException {
        s.defaultReadObject();
        this.n = HashCommon.arraySize(this.size, this.f);
        this.maxFill = HashCommon.maxFill(this.n, this.f);
        this.mask = this.n - 1;
        final double[] key2 = new double[this.n + 1];
        this.key = key2;
        final double[] key = key2;
        final Object[] value2 = new Object[this.n + 1];
        this.value = (V[])value2;
        final V[] value = (V[])value2;
        int i = this.size;
        while (i-- != 0) {
            final double k = s.readDouble();
            final V v = (V)s.readObject();
            int pos;
            if (Double.doubleToLongBits(k) == 0L) {
                pos = this.n;
                this.containsNullKey = true;
            }
            else {
                for (pos = ((int)HashCommon.mix(Double.doubleToRawLongBits(k)) & this.mask); Double.doubleToLongBits(key[pos]) != 0L; pos = (pos + 1 & this.mask)) {}
            }
            key[pos] = k;
            value[pos] = v;
        }
    }
    
    private void checkTable() {
    }
    
    final class MapEntry implements Double2ReferenceMap.Entry<V>, Map.Entry<Double, V> {
        int index;
        
        MapEntry(final int index) {
            this.index = index;
        }
        
        MapEntry() {
        }
        
        public double getDoubleKey() {
            return Double2ReferenceOpenHashMap.this.key[this.index];
        }
        
        public V getValue() {
            return Double2ReferenceOpenHashMap.this.value[this.index];
        }
        
        public V setValue(final V v) {
            final V oldValue = Double2ReferenceOpenHashMap.this.value[this.index];
            Double2ReferenceOpenHashMap.this.value[this.index] = v;
            return oldValue;
        }
        
        @Deprecated
        public Double getKey() {
            return Double2ReferenceOpenHashMap.this.key[this.index];
        }
        
        public boolean equals(final Object o) {
            if (!(o instanceof Map.Entry)) {
                return false;
            }
            final Map.Entry<Double, V> e = (Map.Entry<Double, V>)o;
            return Double.doubleToLongBits(Double2ReferenceOpenHashMap.this.key[this.index]) == Double.doubleToLongBits((double)e.getKey()) && Double2ReferenceOpenHashMap.this.value[this.index] == e.getValue();
        }
        
        public int hashCode() {
            return HashCommon.double2int(Double2ReferenceOpenHashMap.this.key[this.index]) ^ ((Double2ReferenceOpenHashMap.this.value[this.index] == null) ? 0 : System.identityHashCode(Double2ReferenceOpenHashMap.this.value[this.index]));
        }
        
        public String toString() {
            return new StringBuilder().append(Double2ReferenceOpenHashMap.this.key[this.index]).append("=>").append(Double2ReferenceOpenHashMap.this.value[this.index]).toString();
        }
    }
    
    private class MapIterator {
        int pos;
        int last;
        int c;
        boolean mustReturnNullKey;
        DoubleArrayList wrapped;
        
        private MapIterator() {
            this.pos = Double2ReferenceOpenHashMap.this.n;
            this.last = -1;
            this.c = Double2ReferenceOpenHashMap.this.size;
            this.mustReturnNullKey = Double2ReferenceOpenHashMap.this.containsNullKey;
        }
        
        public boolean hasNext() {
            return this.c != 0;
        }
        
        public int nextEntry() {
            if (!this.hasNext()) {
                throw new NoSuchElementException();
            }
            --this.c;
            if (this.mustReturnNullKey) {
                this.mustReturnNullKey = false;
                return this.last = Double2ReferenceOpenHashMap.this.n;
            }
            final double[] key = Double2ReferenceOpenHashMap.this.key;
            while (--this.pos >= 0) {
                if (Double.doubleToLongBits(key[this.pos]) != 0L) {
                    return this.last = this.pos;
                }
            }
            this.last = Integer.MIN_VALUE;
            double k;
            int p;
            for (k = this.wrapped.getDouble(-this.pos - 1), p = ((int)HashCommon.mix(Double.doubleToRawLongBits(k)) & Double2ReferenceOpenHashMap.this.mask); Double.doubleToLongBits(k) != Double.doubleToLongBits(key[p]); p = (p + 1 & Double2ReferenceOpenHashMap.this.mask)) {}
            return p;
        }
        
        private void shiftKeys(int pos) {
            final double[] key = Double2ReferenceOpenHashMap.this.key;
            int last = 0;
        Label_0009:
            while (true) {
                pos = ((last = pos) + 1 & Double2ReferenceOpenHashMap.this.mask);
                double curr;
                while (Double.doubleToLongBits(curr = key[pos]) != 0L) {
                    final int slot = (int)HashCommon.mix(Double.doubleToRawLongBits(curr)) & Double2ReferenceOpenHashMap.this.mask;
                    Label_0118: {
                        if (last <= pos) {
                            if (last >= slot) {
                                break Label_0118;
                            }
                            if (slot > pos) {
                                break Label_0118;
                            }
                        }
                        else if (last >= slot && slot > pos) {
                            break Label_0118;
                        }
                        pos = (pos + 1 & Double2ReferenceOpenHashMap.this.mask);
                        continue;
                    }
                    if (pos < last) {
                        if (this.wrapped == null) {
                            this.wrapped = new DoubleArrayList(2);
                        }
                        this.wrapped.add(key[pos]);
                    }
                    key[last] = curr;
                    Double2ReferenceOpenHashMap.this.value[last] = Double2ReferenceOpenHashMap.this.value[pos];
                    continue Label_0009;
                }
                break;
            }
            key[last] = 0.0;
            Double2ReferenceOpenHashMap.this.value[last] = null;
        }
        
        public void remove() {
            if (this.last == -1) {
                throw new IllegalStateException();
            }
            if (this.last == Double2ReferenceOpenHashMap.this.n) {
                Double2ReferenceOpenHashMap.this.containsNullKey = false;
                Double2ReferenceOpenHashMap.this.value[Double2ReferenceOpenHashMap.this.n] = null;
            }
            else {
                if (this.pos < 0) {
                    Double2ReferenceOpenHashMap.this.remove(this.wrapped.getDouble(-this.pos - 1));
                    this.last = -1;
                    return;
                }
                this.shiftKeys(this.last);
            }
            final Double2ReferenceOpenHashMap this$0 = Double2ReferenceOpenHashMap.this;
            --this$0.size;
            this.last = -1;
        }
        
        public int skip(final int n) {
            int i = n;
            while (i-- != 0 && this.hasNext()) {
                this.nextEntry();
            }
            return n - i - 1;
        }
    }
    
    private class EntryIterator extends MapIterator implements ObjectIterator<Double2ReferenceMap.Entry<V>> {
        private MapEntry entry;
        
        public MapEntry next() {
            return this.entry = new MapEntry(this.nextEntry());
        }
        
        @Override
        public void remove() {
            super.remove();
            this.entry.index = -1;
        }
    }
    
    private class FastEntryIterator extends MapIterator implements ObjectIterator<Double2ReferenceMap.Entry<V>> {
        private final MapEntry entry;
        
        private FastEntryIterator() {
            this.entry = new MapEntry();
        }
        
        public MapEntry next() {
            this.entry.index = this.nextEntry();
            return this.entry;
        }
    }
    
    private final class MapEntrySet extends AbstractObjectSet<Double2ReferenceMap.Entry<V>> implements Double2ReferenceMap.FastEntrySet<V> {
        @Override
        public ObjectIterator<Double2ReferenceMap.Entry<V>> iterator() {
            return new EntryIterator();
        }
        
        @Override
        public ObjectIterator<Double2ReferenceMap.Entry<V>> fastIterator() {
            return new FastEntryIterator();
        }
        
        public boolean contains(final Object o) {
            if (!(o instanceof Map.Entry)) {
                return false;
            }
            final Map.Entry<?, ?> e = o;
            if (e.getKey() == null || !(e.getKey() instanceof Double)) {
                return false;
            }
            final double k = (double)e.getKey();
            final V v = (V)e.getValue();
            if (Double.doubleToLongBits(k) == 0L) {
                return Double2ReferenceOpenHashMap.this.containsNullKey && Double2ReferenceOpenHashMap.this.value[Double2ReferenceOpenHashMap.this.n] == v;
            }
            final double[] key = Double2ReferenceOpenHashMap.this.key;
            int pos;
            double curr;
            if (Double.doubleToLongBits(curr = key[pos = ((int)HashCommon.mix(Double.doubleToRawLongBits(k)) & Double2ReferenceOpenHashMap.this.mask)]) == 0L) {
                return false;
            }
            if (Double.doubleToLongBits(k) == Double.doubleToLongBits(curr)) {
                return Double2ReferenceOpenHashMap.this.value[pos] == v;
            }
            while (Double.doubleToLongBits(curr = key[pos = (pos + 1 & Double2ReferenceOpenHashMap.this.mask)]) != 0L) {
                if (Double.doubleToLongBits(k) == Double.doubleToLongBits(curr)) {
                    return Double2ReferenceOpenHashMap.this.value[pos] == v;
                }
            }
            return false;
        }
        
        public boolean remove(final Object o) {
            if (!(o instanceof Map.Entry)) {
                return false;
            }
            final Map.Entry<?, ?> e = o;
            if (e.getKey() == null || !(e.getKey() instanceof Double)) {
                return false;
            }
            final double k = (double)e.getKey();
            final V v = (V)e.getValue();
            if (Double.doubleToLongBits(k) == 0L) {
                if (Double2ReferenceOpenHashMap.this.containsNullKey && Double2ReferenceOpenHashMap.this.value[Double2ReferenceOpenHashMap.this.n] == v) {
                    Double2ReferenceOpenHashMap.this.removeNullEntry();
                    return true;
                }
                return false;
            }
            else {
                final double[] key = Double2ReferenceOpenHashMap.this.key;
                int pos;
                double curr;
                if (Double.doubleToLongBits(curr = key[pos = ((int)HashCommon.mix(Double.doubleToRawLongBits(k)) & Double2ReferenceOpenHashMap.this.mask)]) == 0L) {
                    return false;
                }
                if (Double.doubleToLongBits(curr) != Double.doubleToLongBits(k)) {
                    while (Double.doubleToLongBits(curr = key[pos = (pos + 1 & Double2ReferenceOpenHashMap.this.mask)]) != 0L) {
                        if (Double.doubleToLongBits(curr) == Double.doubleToLongBits(k) && Double2ReferenceOpenHashMap.this.value[pos] == v) {
                            Double2ReferenceOpenHashMap.this.removeEntry(pos);
                            return true;
                        }
                    }
                    return false;
                }
                if (Double2ReferenceOpenHashMap.this.value[pos] == v) {
                    Double2ReferenceOpenHashMap.this.removeEntry(pos);
                    return true;
                }
                return false;
            }
        }
        
        public int size() {
            return Double2ReferenceOpenHashMap.this.size;
        }
        
        public void clear() {
            Double2ReferenceOpenHashMap.this.clear();
        }
        
        public void forEach(final Consumer<? super Double2ReferenceMap.Entry<V>> consumer) {
            if (Double2ReferenceOpenHashMap.this.containsNullKey) {
                consumer.accept(new BasicEntry(Double2ReferenceOpenHashMap.this.key[Double2ReferenceOpenHashMap.this.n], Double2ReferenceOpenHashMap.this.value[Double2ReferenceOpenHashMap.this.n]));
            }
            int pos = Double2ReferenceOpenHashMap.this.n;
            while (pos-- != 0) {
                if (Double.doubleToLongBits(Double2ReferenceOpenHashMap.this.key[pos]) != 0L) {
                    consumer.accept(new BasicEntry(Double2ReferenceOpenHashMap.this.key[pos], Double2ReferenceOpenHashMap.this.value[pos]));
                }
            }
        }
        
        @Override
        public void fastForEach(final Consumer<? super Double2ReferenceMap.Entry<V>> consumer) {
            final BasicEntry<V> entry = new BasicEntry<V>();
            if (Double2ReferenceOpenHashMap.this.containsNullKey) {
                entry.key = Double2ReferenceOpenHashMap.this.key[Double2ReferenceOpenHashMap.this.n];
                entry.value = Double2ReferenceOpenHashMap.this.value[Double2ReferenceOpenHashMap.this.n];
                consumer.accept(entry);
            }
            int pos = Double2ReferenceOpenHashMap.this.n;
            while (pos-- != 0) {
                if (Double.doubleToLongBits(Double2ReferenceOpenHashMap.this.key[pos]) != 0L) {
                    entry.key = Double2ReferenceOpenHashMap.this.key[pos];
                    entry.value = Double2ReferenceOpenHashMap.this.value[pos];
                    consumer.accept(entry);
                }
            }
        }
    }
    
    private final class KeyIterator extends MapIterator implements DoubleIterator {
        public KeyIterator() {
        }
        
        @Override
        public double nextDouble() {
            return Double2ReferenceOpenHashMap.this.key[this.nextEntry()];
        }
    }
    
    private final class KeySet extends AbstractDoubleSet {
        @Override
        public DoubleIterator iterator() {
            return new KeyIterator();
        }
        
        public void forEach(final DoubleConsumer consumer) {
            if (Double2ReferenceOpenHashMap.this.containsNullKey) {
                consumer.accept(Double2ReferenceOpenHashMap.this.key[Double2ReferenceOpenHashMap.this.n]);
            }
            int pos = Double2ReferenceOpenHashMap.this.n;
            while (pos-- != 0) {
                final double k = Double2ReferenceOpenHashMap.this.key[pos];
                if (Double.doubleToLongBits(k) != 0L) {
                    consumer.accept(k);
                }
            }
        }
        
        public int size() {
            return Double2ReferenceOpenHashMap.this.size;
        }
        
        @Override
        public boolean contains(final double k) {
            return Double2ReferenceOpenHashMap.this.containsKey(k);
        }
        
        @Override
        public boolean remove(final double k) {
            final int oldSize = Double2ReferenceOpenHashMap.this.size;
            Double2ReferenceOpenHashMap.this.remove(k);
            return Double2ReferenceOpenHashMap.this.size != oldSize;
        }
        
        public void clear() {
            Double2ReferenceOpenHashMap.this.clear();
        }
    }
    
    private final class ValueIterator extends MapIterator implements ObjectIterator<V> {
        public ValueIterator() {
        }
        
        public V next() {
            return Double2ReferenceOpenHashMap.this.value[this.nextEntry()];
        }
    }
}
